{"naam": "Beckerman, S.M.", "partij": "SP", "heeftTwitter": true, "twitterHandle": "sandrabeckerman", "follows": ["sbiharie80", "julianbushoff", "farahmbazzi", "hannahvbinsbabe", "jacobinnl", "dino_comics", "rebeccasolnit", "tonvanderham", "roelof_bosma", "petermichiel", "tboskers", "spjongeren", "geerlingjolanda", "noah_vetter_", "stationsflat", "kuijtmarin", "marijnfrank", "kustawbessems", "pompenburger", "caring_vets", "danielproud", "heleenlansink", "basweegberg", "ishetalveilig", "studiosalto", "studio1902", "graceblakeley", "marcelhulshof8", "erdbebende", "lianedenhaan", "joshuaphilll", "pegasfragmenten", "paapst", "bertwierenga2", "dejulioagustin", "anjodehaan", "reyerboxem", "niiwino", "yv_hiemstra", "hogenoorden", "agblanken", "rijksbm", "zarahsultana", "eiecampaign", "casparvdberg", "victivincimus24", "fraudebauer", "mdevriesnature", "jeremievzeist", "tk_moties", "de_federatie", "pvdaindekamer", "sofie_merckx", "annedelespaul", "erfgoedvacature", "kploegman", "j_vollenbroek", "mauritsgemmink", "miekemegawati", "meteoroodescho1", "derkstokmans", "felixvoogt", "jwerisman", "alexdatema", "peteroosterhof2", "redderingx", "johan_emmens", "joksjanssen", "caringfarmers", "heleenekker", "sijan104", "johanhamster", "jonhuus", "gertjanplets", "b72542976", "f_kamminga", "santurksema", "kbhagen", "johanfretz", "lutgielen1", "weirdmedieval", "lbgroningen", "levederepubliek", "mrmontfoort", "dierencoalitie", "mansschepers", "stevenpelten", "sylvanabij1", "delverlaura", "wesleypechler93", "goossen71", "igorwijnker", "evawaterbolk", "pedegro", "pietskoe", "eelkea", "derksauer", "katipiri", "aukehulst", "ikwilpret", "lientje1967", "sp_veenendaal", "judyblankmusic", "beenjasper", "gerard1740", "stasmijnbouw", "swaalfke", "sandra77226149", "groningengas", "mariskasloot", "danielkoerhuis", "lambeckjantien", "dgennep", "wvgent", "s_vanteutem", "bouhlelheidi", "yvonnemorselt", "klaasjepen", "liesbeth050", "robertrosendal", "michielroesink", "schilderplezier", "timsjongers", "martijnbax12", "bettievveen", "hanshaze1", "hierisirisblog", "mirjambikker", "manuelame", "tkameraadschap", "shyama_ver", "hertintveld", "leilanifarha", "woonverzet", "woonstrijd", "neluzzz", "benhetwelzat", "afienavanzanten", "merimurica", "denkjewel", "wndngn", "megonzalezpere2", "soltrumbo", "octaview", "melissa_ydra", "woonopstand", "woonprotest", "smeerlingantiek", "marrigjerikken", "a_abdillahi", "kampeerstad", "mooigrunnen", "brearkeologi", "sannemeijerblog", "niettekoop", "kpleefbaar", "unreachableone", "vprotegenlicht", "rce_erfgoed", "voedselanders", "guusgeurts", "hgl_mirjamaalfs", "broekroelofsp", "batch1588", "stopverkoophvh", "rechtopdestad", "stephanvbaarle", "buitengebieden", "gwenvaneijk", "kjonker33", "jandevries2005", "tjeerdd66", "derkboswijk", "aukjedevries", "inge75", "supermarieke", "oeavr_", "muntz_thomas", "davidwengrow", "kauthar_", "leonievestering", "wimjmvoermans", "sietce", "paulwatt1232", "gosserd", "huuboosterhuis", "raoulboucke", "janheinstrop", "bschohaus", "bplaatje", "wendelmoetl", "jeske_jongerius", "fboulakjar", "sennamaatoug", "tweebosbuurt", "derooijnathalie", "sinancan77", "homes4alluk", "kimputters", "marxdays", "killermartinis", "vliksboz", "gerardloos3", "kristierongen", "jurjonker", "wijgroninger", "martjankuit", "lotusfriede", "huawei", "habtamudehoop", "pieter_grinwis", "gorterarne", "aptoniem", "grand_nb", "ineskostic", "markharbers", "maykezandstra", "gadverdharrie", "hofmard", "rf_hfc", "michielvnispen", "ernstkuiper", "laurabromet", "fokkesukke", "janetgroenevel3", "overlistener", "patrickdextervc", "dirk_van_dam", "robert_limbach", "cpminnaard", "natbrusgaard", "asielgroningen", "wdekanter", "precwoonvormen", "pieterkleinntr", "evarovers", "janinedewit", "ploumenlilianne", "larsruiter", "p_wagenaar", "sanvanlan", "sjenettt", "hennypare", "fritsterpstra", "abakker28", "sjaantje_p", "pieteromtzigt", "kovanhuissteden", "nicoleveijkern", "mbreedveld", "energyfeminist", "lesley_arp", "hoefslootrick", "bobdegreef", "markduursma", "spjongeren070", "daphne_breugel", "bram_roovers", "diyarjassim", "daphnetenkloo", "sp_eerstekamer", "chrisjulien", "woutervdenbrink", "sannetenwolde", "wjdannijs", "fbraamhorst", "rosaluxglobal", "rosaluxstiftung", "rosaluxeuropa", "simonevandijken", "cisvanaken", "stemmingen", "lukkezen", "molenheerdt", "onderhoudsarmoe", "jhterpstra", "meerbomenn", "xandragrwold", "archaeologyart", "gastransitie", "janhoedeman", "itookyourname", "gwarink", "qpjbourgeois", "tombjorklundart", "lnbdublin", "handelanders", "ennozuidema", "gajusscheltema", "arjamari", "bwvmeijer", "eddy_terstall", "maaikeschoon", "stutensteun", "enwijdan", "huurdersnetwerk", "moptredens", "floormilikowski", "fenokkio", "eobroin", "kirsten_grunn", "agnes19692", "postemamarja", "davidrkadler", "pitrmanova", "martindrent", "stcomiteschone1", "tijdvooreten", "federatiehcs", "kopspvv", "mlathouwers", "dietukkerfries", "histo_in_rusto", "traumabeertje", "evdb21", "zooarchgia", "kimvankeken", "municipaldreams", "evavanesch", "lisewitteman", "basvandervoort", "vrijlinks", "matthijs85", "emkemol", "evahoeke", "gbbgroningen", "joram_krol", "just_richardson", "ronanburtenshaw", "koninklijkmassa", "mariannezw", "profdanhicks", "sterknikki", "cihanugural", "jannievisscher", "orlamcdonald", "bigmeaninternet", "wa_korrewegwijk", "wa_oosterpark", "tristanbraakman", "erikronnes", "avinashbhikhie", "randymartens", "veldejean", "jwroodbeen", "wiebesquotes", "jwstartop", "steundhani", "maryloumcdonald", "jversijde", "nlijssennagger", "matthijssienot", "fapbv", "hilversumuit", "maaikedv", "mourningmarty", "irenevdlinde", "willemwiskerke", "joetencate1", "tamcgath", "mauricejcasey", "archeokluit", "miesschipper", "henkgerritsen4", "jeroenstans", "lucasbenschop", "1848nl", "basvansluis", "baspaternotte", "gfrieling", "gasbelt", "bevingmeter", "luciemiddlemiss", "epah_eu", "harrimus", "engagercost", "aoc", "marceldrenth61", "woondrama", "charlottehvnl", "1969arjan", "advocaathuur", "natascharosa", "floripasdelaban", "sonnyspek", "berryhaanuhm", "klimaatstaking", "mrgeorgeclarke", "slopsemasr", "coenvdven", "joostvullings", "marktraa", "spapeldoorn", "henri_kerkdijk", "sandrajagesar", "giedi1", "markvanesveld", "arbitercafe", "ldeheritage", "kstrobi", "cwbbakker", "muratmemis_sp", "joris_pvda", "georgemonbiot", "groningervlag", "irdv", "arnonimiteit", "rvgrunn", "nynke", "alieskap66", "janvandevenis", "barnabypace", "dijkdebbie", "marijevanhell", "hansbrusselmans", "jokehermsen", "lotjebeeft", "granbywg", "granbyworkshop", "granby4streets", "j_savelkouls", "coxroger", "jaaptielbeke", "hilbrandp", "klaaseverts", "michellesmelik", "peterwvandet", "edwinvanderaa76", "houtsebastiaan", "klimaatmars", "mirrorpiggy", "gilian_schout", "bielsmajaap", "kammingafred", "tribunemagazine", "tegenmijnbouw", "jongerentopnl", "mthybaut", "gerritrentier", "markvandijken2", "patrieciaa", "dennismolema", "royveninga", "ct_teunissen", "evaakerboom", "leoniesazias", "vanderveen_erik", "jamansholt", "paulsmeulders", "trudyaleven", "tiesjoosten", "charlesdelberto", "stopzoutwinning", "thiemoheilbron", "beablokhuis1", "samanthajcsmith", "anjawoortman", "josjebeukema", "franshempen", "ericherben", "youjonker", "annelies", "freek_md", "tomvanderlee", "ecn", "michielhulshof", "lu_ons", "venema", "emmanuelguaglia", "theojans1", "pelleberting", "keeskodde", "erafoen1", "industriall_gu", "staarink", "rubenvdmeer", "m_nke", "bschollema", "jan_reilink", "vincentlublink", "energie_vanons", "wijnenwhiskyetc", "derouwh", "zonnedorpen", "samgerrits", "kuipersate", "schadeloketimg", "awhiemstra", "advaya", "erikdejonge1967", "mgeschiere", "deburgemeester", "bootstrapcook", "pieterplass", "eefjevanduin", "kadijkm", "coertfossen", "jolanda633mini", "dhabirecorder", "keilmesser", "ankiepetersen", "studiomarcha", "willemgroen050", "metagnesbakker", "joriendelege", "jantinarusschen", "tjerkbos", "saskiagold", "rebekkatimmer", "prehistoryrmo", "goos_over_ict", "mariskadelange", "univgroningen", "gasbevingenport", "freeksels", "marcogrimmon", "kamermoties", "kittyjong1", "klimaatactie", "strmvrsnllng", "grontzet", "paulinebroekema", "tihangepensioen", "rozemahilbrand", "evilbmcats", "sven_jach", "ingelengton", "statusborssele", "statusdoel", "statustihange", "co2ntramine", "statusemsland", "lisetmeddens", "350europe", "mdmmrs", "mheuw", "ruimtemaker", "karinspaink", "roxanevaniperen", "archeologiezh", "klimaatzuster", "coltmancindy", "kvgalen", "woningnieuws", "lobbywatchnl", "350", "linedewitte", "kajsaollongren", "sp_alphenadrijn", "bram_reinders", "samenomnl", "vjprofs", "abpfossielvrij", "lexdeboer", "lilianschrijft", "mcouzy", "jhmommers", "isgoedhoor", "verhoog_e", "actionaid_nl", "paxvoorvrede", "woinactie", "kerphal", "margalithk", "inkidejonge", "henribontenbal", "joriswijnhoven", "gverbaan", "janineabbring", "wilminevdbosch", "remcodb", "marjanminnesma", "henkstrikkers", "laurievdburg", "bartlankester", "fvonderwijs", "brammertsp", "fem015", "bock_bettina", "es_its", "ronaldpaping", "aedesnet", "woonbond", "nieuwscorpos", "safehomesforall", "bloeiendverzet", "gerkebrouwer", "mhanemaaijer", "panverlo", "codyhochstenb", "oosterparkers", "khadijaarib", "alexburlini", "reneschellekens", "danielle_h_be", "ewoutirrgang", "liekemarsman", "geert_ritsema", "timficheroux", "bewogenburger", "die_linke_nds", "energiekoepel", "dewereldmorgen", "missykel", "stellingdames", "ijzendoornv", "willem_meiborg", "luchtwachtkld", "stopgenx", "duutzaam", "mkeulemans", "leosonneveld", "daniellohues", "inoordhoff", "hilmabolsman", "pjboelhouwer", "corporatieudate", "justinedus", "brambuscher", "platformlondon", "moeders_grunn", "sandersas", "raoulhedebouw", "pmavanzutphen", "martennauta", "attjekuiken", "gr_monument", "lammertvanraan", "frenkvolt", "bartvberkel", "stijnv86", "petra_molenaar", "sunvandijk", "querienvelter", "obk", "grunnegerpower", "mazaskatalks", "tufawon", "nataanii_means", "shellwatch", "fruys", "peerderijk", "dr1k", "psch90", "leolucassen", "markmiddel", "ericchrsmit", "femkemerel", "de_kerk_odd", "mrtbollen", "fossielvrijnl", "fossielvrij", "shel_den_haag", "bewisenonuclear", "lakanieuws", "linksfraktion", "dielinke_hh", "demacagro", "ffculturenl", "jagraag", "jeltehom", "myrthevdmeer", "wassenbergfrank", "op1npo", "spheerlen", "achrafglobal", "despanning", "graannaarbanaan", "wouterdewinther", "m_ettema", "irisveenvorser", "ami_gest", "everthassink", "saskiag_md", "karenvdeinden", "ol_tjoard", "donaldpols", "naomiaklein", "berndandeweg", "pietervvol", "vergnesexperts", "lzwakhals", "fd_energie", "energeia_nieuws", "arnorutte", "henknijboer", "kordwarshuis", "kiradekker", "wybrenvanhaga", "marjoleinedevos", "njrjeugddebat", "njrtweets", "sarahdobbe", "carladikfaber", "jesseklaver", "keesvee", "groenliesbeth", "svveldhoven", "andrebosman", "m_everling", "jellejolles", "annekuik", "hetdordts", "alexanderbakker", "naardemaan", "dankgroningen", "pronouk", "bnrduurzaam", "roosvgelderen", "sp_drenthe", "jkbonline", "irisvdkolk", "gasschandaal", "marjasol", "luyte", "arnoldveeman", "rolfhut", "sanderdekker", "anjavanduren", "freekjonge", "politiekinneder", "hildevanderpas", "commonsnetwork", "s1nancankaya", "antjediertens", "claricegargard", "ja_bakker", "switchedonldn", "niekstam", "chavezdaniel", "kahrawl", "clblanchet", "m_wiersma", "jossedevoogd", "rensvl", "martijnklungel", "suzanne_gl", "agnesmuldercda", "changerism", "braam81", "pmarijnissen1", "raymondjousma", "mahiralkaya", "fritsbeckerman", "ionicasmeets", "maaikeborst", "lsteinfort", "mathijsbouman", "kenloachsixteen", "zonder_de_nam", "reinalda", "lindavvermeulen", "lvogelpoel", "oecd_stat", "oecd", "oecd_social", "eu_eurostat", "paul1kirby", "roodamsterdam", "roodnijmegen", "jamesworthy", "foodwatch_nl", "bertpeterse", "mpatijn", "phvmulligen", "hilliedekoe", "ilse_z", "pointer_kroncrv", "wimboevink", "spikedonline", "ozcanakyol", "fatahblack", "michelvrschuren", "gr_landschap", "hadjar", "jdnijland", "fossilfreetue", "biancakaathoven", "welkomgasberaad", "siebelinkjeroen", "tom_post", "gro_perspectief", "petities", "cemlacin", "bartissimus", "soech", "ruudkuin", "geertenwaling", "ajplus", "marijnstolk_", "derde_helft", "zorgbelang", "skipr", "zorggids", "oogstgroningen", "dorinesibbes", "meneer_stijn", "nrc_opinie", "denisesluijs", "platformsampl", "robinyzerman", "niekus_", "bellhooksinst", "ingezwerver", "magdasmink", "michaelujacobs", "yurrewieken", "hgo_groningen", "neverfal_", "floggingmolly", "jhoedemaekers", "wgvanderwiel", "marcoglastra", "paultdebeer", "sciaccacorry", "fossielvrijgro", "edwinpasv", "openmonumentdag", "derwin9999xl", "nlzorgfonds", "theocoskun", "itsmunganyende", "erasmusmag", "teunvandekeuken", "rdstad", "fcgroningen", "resourcewur", "milieudefensie", "lalalalinder", "ideeenbankg", "drk75", "vatanhuzeir", "ezsther", "kirstendewrede", "barttrouw", "rolfschipper", "sp_swf", "lamyaea", "bartcrezee", "stoptwente", "ellaweggen", "oostveenm", "marijn_kroes", "kortschrijvers", "martijnkatan", "sp_prov_utrecht", "roodutrecht", "tudelta", "forensicchemist", "robertdputnam", "rengervandehoef", "_investico", "rooddelft", "brandpunt_plus", "irenevstaveren", "spdelfttemp", "ahkleinknecht", "hansdegeus", "ellism88", "meltemokcu", "ewa_slutzky", "seachtar", "womenof1916", "marymcauliffe4", "theirishrev", "stopdebommen", "weekbladmare", "socialevraagst", "profhoekstra", "cunerac", "ruthpeetoom", "renepaas", "trouwgroen", "hansmarijnissen", "_lizmain", "trouw", "killermike", "tammobeishuizen", "brendaharsveld", "dijkstra_laura", "berniesanders", "sensanders", "ivanwolffers", "lbatstra", "caal", "gjtenbrink", "solidair_org", "eduard_schmidt", "arnoudlagendijk", "lisawesterveld", "marijtjejongsma", "reclaimproject", "dubnieuws", "jacobin", "annemarieheite", "indraromgens", "folia", "1opstraat", "ndridder", "marloesvdsommen", "johanverspay", "archeologisch", "marijnissenma", "jeremycorbyn", "owenjones84", "peterpolder", "menno_tamminga", "seadanourhussen", "zihniozdil", "anoushanzume", "mariammaslouhi", "ncgroningen", "robvanhattum", "denieuwsbv", "hetmaagdenhuis", "uniofcolour", "jurjenvdb", "vpropoesjes", "frankahummels", "westerwolde", "vancalmthout", "jet_bussemaker", "klamer_arjo", "mejudice", "kkoedijk", "hpvandalen", "spbreda", "basmaes", "dijkvangijs", "thomas_c_a", "urgenda", "fgeerdink", "pfrug", "trechterbekers", "studentenbond", "asva_vakbond", "gilsben", "arnevanderwal", "rzuaslan", "chrisklomp", "perriehoekstra", "rhdijkgraaf", "greenhousenyt", "2525", "facultyforward", "s_gesthuizen", "humanitiesrally", "femkeepsp", "b_v_apeldoorn", "scitransit", "platformhnu", "zizek_uni", "rethinkuu", "danhf", "lindseyagerman", "vostog", "tariqali_news", "dnpp_rug", "smrwsk", "archeodagen", "theunissenties", "vriensarcheo", "dylanvr", "davidhollanders", "dewaremerijn", "pvdagroningen", "mhairiblack", "mazzucatom", "josephestiglitz", "stiglitzian", "jaapselles", "riet_de_wit", "hellahueck", "d66psgroningen", "provstatenpvhn", "groningerbelang", "ns_online", "renebolle", "edwinatema", "yanisvaroufakis", "mikoflohr", "theotoebosch", "eefstof", "hansslooter", "paulkusters050", "roelsint", "gervanunen", "archasa", "hopersbureau", "bursaal_nee", "adacolau", "denacht", "eugeniestolk", "fernandezamster", "ftm_nl", "rcbregman", "rienkjkamer", "somo", "fleurgraeper", "siegbertvdvelde", "davidgraeber", "adjunctaction", "dnugroningen", "jafaripeyman", "f1a38d396c0a403", "wubbyl", "arjennolles", "bebkruize", "robertdewit1990", "youngunitednl", "bramschmaal", "fightfor15ia", "mertensfloor", "henkhensen", "pietvandijken", "marioomiskovic", "grtredactie", "diederikolders", "chifightfor15", "wilma_swarts", "dnu_024", "rethinkuva", "bloarkopstront", "bijkerj", "janwolters2", "hannekejagersma", "alfred_meester", "dossiergrunn", "arjenlubach", "estherouwehand", "karinshantidevi", "nicoheijmanssp", "sikkom050", "mtekol", "left_eu", "europeanleft", "gas_groningen", "ardag", "hmeendering", "keeswillemen43", "oostgr", "cecilevisscher", "archeoloog", "stukroodvlees", "henriswinkels", "hakhverdian", "historyinpics", "pe_en_rinus", "karapetian_a", "iketeuling", "archeonet", "noorkrista", "reportingwomen", "berkenbosch", "rosatimmer", "medewsionsberg", "pieterdehart", "studiorobbie", "ernaberends", "erikflentge", "cschaeffersp", "spamersfoort", "ramonvos", "marijkejj", "luukvangeffen", "angelscho", "peter_mertens", "pvdabelgie", "histwesterwolde", "museuminfo", "marlenebakker", "baacbv", "hannedrost", "dielinkenrw", "wim2103", "goosmdeboer", "archol_bv", "archeologieweb", "archeopubliek", "awn_archeologie", "raaperfgoed", "tgvpresentaties", "mainavdzwan", "esmoves2", "fnv", "sodmnl", "noordlive", "wimsomers", "archaeologymag", "openaccessarch", "fjdeboer44", "sp_fryslan", "spnoordholland", "worldarchaeo", "currentarchaeo", "archscot", "huisvanhilde", "ottobrinkkemper", "bronzeageeurope", "erfgoedwet", "spveenendaal", "garynobles", "aardbevingnl", "statistiekcbs", "koning_nl", "therocker57", "annekeduit1", "maevelevie", "marcointveldt", "nettieengels", "marcoout", "josswartjes_sp", "geelhoedwendy", "bartvermeulen_", "archeon", "hondsruggeopark", "exarc_net", "archeohotspots", "hunebedcentrum", "jurrevandenberg", "stopleenstelsel", "nwilkinbm", "spadjes", "kuitenbrouwer", "swagenknecht", "voxdotcom", "riekvankampen", "dielinke", "katjakipping", "jellebc", "ewaldeng", "mmulder1972", "daanprevoo", "mpvissers", "nicoheijmans", "loesjenl", "spveendamsp", "marten_feenstra", "evrydayfeminism", "15andaunion", "tiersbakker", "sp_amsterdam", "sp026", "lindavoortman", "reminealberts", "fnvjong", "rood_den_bosch", "vesterko", "chasalin", "spleiden", "dijkshoorn", "janbroekema", "bedreigd", "raybeckerman", "archeobanen", "erfgoedstem", "archeologen", "jkleijne", "bioarcholivia", "legoacademics", "pabloiglesias", "thetweetofgod", "joosjedelang", "barrysmit", "tijdschriftnb", "acbodde", "jaapjansen", "robinvdvelden", "tuurelzinga", "basstoffelsen", "pvvkesteren", "babettealma", "janvdmeidenoord", "kjeetje", "cdaprovinciegr", "groningen", "pvddpsgroningen", "vogelvrijeharts", "ashatenbroeke", "wagebeauty", "livingwageuk", "wagemark", "went1955", "symaiah", "sheilasitalsing", "esvanana", "we_love_art_", "bakker_nic", "vrijmandaat", "nambv", "despeld", "cuprovgroningen", "tinecastelijns", "pvlunteren", "bertilfranken", "farshadbashir", "hillymast", "joop_nl", "groningendb", "ddjong", "matthiasvhunnik", "ericsmaling", "amelewe", "jolavandijk", "rootje71", "zwaanesther", "markla94", "bobotaal", "michelmarion", "upworthy", "oghartman", "micheleggermont", "advocaatklaas", "renskehe", "tatumpostema", "sputrecht", "willylourenssen", "cvanbrenk", "benrewinkel", "irma_koopman", "marijnissenl", "socplangron", "jhvandersanden", "spnijmegen", "alexvervoort", "nilsmuller", "margawubbema", "gerritspeelman", "tklootsema", "nienkehoman", "wiebevdploeg", "gvangalen", "wimhut", "grietjeu", "dianagruben", "tjeerdvd", "evartvnoord", "moralmondays", "fightfor15", "raiseupthesouth", "optimistsprime", "sp_slochteren", "jantjefens", "erikmaassensp", "mussel47", "gezinsbode", "lindavisser82", "alvast76", "janmuter", "paulabvo", "nos", "volkskrant", "nrc", "decorrespondent", "robwijnberg", "degroene", "danielhake", "joostvankeulen", "wmoorlag", "markboumans", "ronaldmvisser", "tweleer", "reuvensdagen", "irarchaeology", "sidestonepress", "ukrantgroningen", "wouter_gk", "archaeopress", "leidenarchaeo", "girlwithtrowel", "ls_hogeland", "sp_vlaardingen", "doededevries", "grootgroningen", "evalienvers", "evertevertidema", "gvdven", "arnouthoekstra", "nellekedegraaf", "rm_oudheden", "bjvlonk", "anneellenp", "jeroenvandijen", "baskrajenbrink", "hulshoflh", "truusvankleef", "ijzebrandrijzeb", "gerritjansteenb", "brouns_p", "martinefeenstra", "henkstaghouwer", "laurakassandra", "romkevisser", "mirjamwulfse", "schokkendgronin", "lesmanj", "bitcoinskopeneu", "fnvvoorzorg", "stienekevdgraaf", "jossp1", "rinzevanderborn", "spmenterwolde", "sphoogezand", "provgroningen", "arthurkamminga", "joycevdwielen", "anjahazekamp", "huubbellemakers", "laurensivens", "gerdasiks", "klootsematjaard", "peterkwint", "jordyclemens", "hvhooft", "vincentbuffinga", "amuller70", "remyvanmannekes", "dvhn_nl", "rtvnoordsport", "mathystenbroeke", "rtvnoord", "johandeveer_", "riagroningen", "frankfutselaar", "eva_db_", "fennaf", "gerrieelfrink", "sandraherkstr", "jaspervandijksp", "serbanescukele", "corrysciacca", "henkvgerven", "renskeleijten", "meyerron", "sprotterdam", "tjitskesiderius", "alex_mink", "ldekleijn", "amerkies", "coppus", "maartenhijink", "erikdevries1979", "spoldambt", "ninekooiman", "dhdewit", "jurgenvdsloot", "andrenobbe", "smitsmarc", "willemnomden", "eelcoeikenaar", "nicolevangemert", "mschollema", "johanteuben", "spgorinchem", "nielsjongerius", "spzuidholland", "spdenhaag", "lieke_smits", "roodjong", "leonbotter", "erikmaassen1", "liesvanaelst", "bartvankent", "robmollink", "manjasmits", "pieterkraaima", "merelstoop", "grannny63", "ericvkaathoven", "sadetkarabulut", "janvdgroen", "reindertbakker", "mldepijper", "hansboerwinkel", "huuralarm040", "paululenbelt", "spwebteam", "ceusw", "chrisgarrit", "stadenharen", "gronstudbond", "martijn611", "sp_pekela", "gic_nl", "evanscheltinga", "oogtv", "rositagrunn", "spnl", "roodgroningen", "emileroemer", "jimmydijk", "nicoletemmink", "lies272", "cristinevandijk", "mechteldvanduin", "daanbrandenbarg", "jhmastenbroek", "spgroningen", "henniehemmes", "spprovgroningen", "lianveenstra", "pimsiegers", "aldoschelvis"]}