{"naam": "Lee, T.M.T. van der", "partij": "Groenlinks", "heeftTwitter": true, "twitterHandle": "tomvanderlee", "follows": ["_cosatu", "chuckpfarrer", "berishalmashi", "julianbushoff", "usambnl", "ministerlnv", "annabellvdb", "jokedejong8", "sandumaiamd", "leendertbeekman", "abaerbock", "raphaellerl", "heronsoccer", "hwsathletics", "zorgmarktde", "overlistener", "zelenskyyua", "daniel_freund", "kyivindependent", "reutersworld", "zij_heeft_het", "diepenmischa", "songulmutluer", "labourstart", "stasmijnbouw", "muhammad_alom26", "henkstaghouwer", "climatehuman", "jpvanypersele", "sanderschimmelp", "annapleijsier", "gilsben", "tsihanouskaya", "rubenbrekelmans", "klinkjan", "s_vanteutem", "mehreenkhn", "ericaschoutennl", "auschwitzmuseum", "alinadanii", "rolfschuttenh", "silvioerkens", "alexsterk_", "jlingevicius", "dassenlaurens", "pieter_grinwis", "wedonthavetime", "the_female_lead", "michaelemann", "geert_ritsema", "leolewin", "alex_engelberg", "vquaschning", "katipiri", "airscottdenning", "d66tom", "nmjuriaan", "robpmulder", "theresphysics", "hausfath", "kloostererik", "ckemfert", "leahstokes", "ipacglobal", "petervanderwal1", "njcaa", "leonijansen", "navalny", "tjc_w_soccer", "njcaa_soccer", "apacheathletics", "thierrybreton", "hijaukudotcom", "sneller", "ministerbz", "anikamolesworth", "robzaagman", "lisaginneken", "kammingarj", "romkedejong", "habtamudehoop", "lucstultiens", "jeroensmitenzo", "wwfnederland", "vlasisoikonomo1", "vp", "raoulboucke", "scapeler", "ploumenlilianne", "potus", "arminlaschet", "kamalaharris", "joebiden", "jengranholm", "gabrielmariya", "scallytara", "sbennettgl", "colinkok84", "romanoboshove", "ifhyder", "toubke", "markbrakel", "serpil__ates", "geert_gabriels", "lauravissenberg", "sennamaatoug", "kauthar_", "andrew_ha65", "kimvsparrentak", "amelieve", "jacindaardern", "jhterpstra", "ingridthijssen", "kindredmotes", "timmermanseu", "samanthajpower", "philosofemme", "priceofoil", "emykoopman", "wolzak", "sarahcpr", "pieterjvanos", "coenvanzwol", "lamyaea", "triodosim", "xanderkoolman", "antonioguterres", "iverberk", "mliebreich", "egerrit", "hasekamp", "carolvaneert", "greeneujournal", "tristanbraakman", "edwardstigter", "deltagroenlinks", "alisterdoyle", "gerrithiemstra", "chrisklomp", "beingfarhad", "tinnevds", "thetweetofgod", "jayinslee", "euclimateaction", "canintl", "climate", "guidovanderwerf", "mzjacobson", "larrouturou", "emorwee", "laurencetubiana", "never_nl", "aoifefleming_vn", "andersen_inger", "lutzjacobi", "railtothecop", "socentnl", "carbonbrief", "vonderleyen", "arakhorst", "schoutenwerner", "anandwrites", "lisavendrik", "jkbonline", "johnfbruno", "rosa11meijer", "solarpapst", "duurzaamactueel", "senatorsaskia", "vincentdekker4", "etm_quintel", "waag", "andyvandyke", "staffandscrip", "eisitman", "mrvandenbroeke", "heleendeconinck", "extinctionr", "rescue_uk", "renepaas", "lffriedman", "jonasdutordoir", "pns_news", "alexsteffen", "mazzucatom", "irenedekruif", "kokkens_", "miaotsoa", "rarohde", "voorzittermkbnl", "remyvanmannekes", "marioomiskovic", "johandeveer_", "mirjam_008", "pieterlossie", "glnijmegen", "melissahaarlem", "zebinder", "dorettecorbey", "larsboelen", "tinuspulles", "waddentweets", "henkdeligt", "youth4climatenl", "meredithgreer", "josjekerkhoven", "dago_nl", "rosalynsaab", "vvte_uvt", "smgaddis", "gretathunberg", "co2_earth", "oomenberlin", "bethdoane", "simondonner", "dvhn_nl", "delta_comm", "ilhanmn", "betoorourke", "peterpolder", "machiavelli_nl", "alexhibbert", "rahmstorf", "aoc", "floripasdelaban", "ericliptonnyt", "khayhoe", "mwkiewiet", "melodydeldjou", "keikelenboom", "saskiag_md", "femkedejong", "benwoldring", "mac_europa", "eefkevdwouw", "andyvdyke", "rob_van_bergen", "nytclimate", "ldemuele", "kevinthehague", "nasaclimate", "ed_hawkins", "annievandepas", "tysonlester", "patricbrunklaus", "galaveldhoen", "sandorgaastra", "vortexbladeless", "sabaloftus", "dutchtechsf", "mdmmrs", "bas_deleeuw", "judgejoyce_", "flyingless", "windeurope", "kittyjong1", "pcgglas", "janhaverkamp", "peerderijk", "strmvrsnllng", "samgerrits", "misstie", "miekepennock", "tijmendevos", "peters_glen", "pkuipersmunneke", "arjanvdhoogen", "gerritrentier", "sianberry", "anne_hidalgo", "georgemonbiot", "manonvanbeek", "platformklimaat", "gerbrandy", "drsimevans", "mrleonardkim", "berendpotjer", "dobbelska", "ndubbelboer", "c_kraack", "mondiaalnieuws", "lindavvermeulen", "karstenklein", "matthijssienot", "vivideconomics", "arianelelieveld", "marieke_werf", "udokock", "rutgerschonis", "onnodwars", "patrickpoelmann", "fscnl", "woutel", "chrismersbergen", "jlvandestreek", "maatschapwij", "krispijnbeek", "rspotweets", "eelcoeikenaar", "isafeelgood", "marissa_c_ryan", "sldelange", "mvdz_", "orlamcdonald", "thijsroovers", "marjawagenaar", "chrisostendorf", "ekostermans", "b_rijlaarsdam", "peterkreko", "windcentrale", "kekoepel", "thierryaartsen", "geraldaouden", "adamrogers2030", "leenvandijke", "heinbruinewoud", "truuskedenh", "jan_salden", "bknoop", "cvnieuwenhuizen", "kirstenhnrds", "jwvdgroep", "davidndii", "michelkerres", "mkvaalst", "frits44869939", "asteroidday", "sasjabeslik", "dienhorn", "henkmulder1", "tom_post", "apvermeulen", "elskem", "albredenoord", "wendesnijders", "csds_uva", "mauricevrooijen", "hielkomerkus", "alfred_meester", "bschollema", "henrikruithof", "catinahenley", "nina_holland", "davedtc", "kimschmitzgl046", "jolandaverburg", "juliamatser", "hans_gruenfeld", "fossielvrijnl", "fritslintmeijer", "sodmnl", "diederikebbinge", "dsa_nl", "adamchandler", "nambv", "jhoedemaekers", "mkbnl", "claudiakammer", "rtvnoord", "gr_monument", "stienekevdgraaf", "noordlive", "mistergreenev", "christianvillee", "loettapaulsen", "thomaspower", "juliefraiture_", "dellenjan", "sspencer", "musicshaster", "gisellekens", "mariekeconomie", "randy_gage", "nienkehoman", "mathijsbeusekom", "yelizdgn86", "johnhall", "keithjkrach", "whatstrending", "jaumefreire", "claudiareiner01", "groen", "myrthehilkens", "carlabrugmanr", "niooknaw", "geasmithbults", "valcardoz", "paulblokhuis", "padraigbelton", "dezorgsector", "psenergygroup", "gewoonrobbert", "walktogether_", "climatemegan", "wattanders", "beaschouten", "steffenie_pape", "profitperclick", "yalee360", "jenvalentino", "josvranken", "matteonatalucci", "o_merk", "erwinwijman", "nrc_opinie", "colettebothof", "solylady", "ednijpels", "bm_visser", "mahiralkaya", "astridpj", "rolvom", "sybrandfrietema", "r_bosman", "r_wessels", "energy4later", "jellsmoor", "rdampartners", "gismis", "callmex", "utrechtactief", "carbonkiller_eu", "iondernemer", "elshofbj", "jomaas", "dirkjankoch", "fluxenergie", "fietsprofessor", "helgavanleur", "hugojanruts", "annemarieheite", "ceritm", "zipconomy", "saskiakluit", "nweawind", "laportpaul", "groeninarnhem", "mkeulemans", "jeroenkerseboom", "robotterdijk", "kimvankeken", "sven_jach", "wemos", "humor_citaten", "gem_nijmegen", "socialevraagst", "pascalguyon", "asmlcompany", "mpnadeboer", "liberaalgroen", "milieucentrum", "leeannemca", "klimaatveranda", "ninjaeconomics", "windunie", "evelientonkens", "jwduyvendak", "marjolijndg", "kenfisher", "windnieuws", "statistiekcbs", "klimaatactie", "kuitenbrouwer", "rekenkamer", "wattisduurzaam", "aikvaneemeren", "joostbrinkman", "erikhuberman", "aukehoekstra", "cbsrnews", "nsb_speakers", "heleboer", "e3g", "jongachterhoek", "joskoniuszek", "thijsdelacourt", "vanbergheneu", "netwerkdem", "welkomgasberaad", "fme_nl", "kleverlaan", "industrysmart", "kornelisblok", "ensoc", "bureaupolitiek", "bartreijnen", "gdninequality", "worsdorfer", "markrutte", "jan_hoekema", "briancgahan", "nielspalmers", "philipdrost", "global_speakers", "tiesjoosten", "sigridkaag", "ipcc_ch", "boeschoten", "cathyvanbeek56", "ministerieezk", "chrismukasa", "euenergynews", "selfhelpafrica", "bv_dijk", "hestervansanten", "hugodejonge", "boyanslat", "smallenbroek", "whazeu", "claudeturmes", "esther_de_lange", "christiannewal", "erikvderwalle", "sacmlavrijssen", "eefinancing", "marleenstikker", "sbrandligt", "nvde", "jelmerevers", "newclimateinst", "tonybosma", "pzo_zzp", "rossdawson", "press4change", "momohandis", "kittykruger", "6billionpeople", "nlr_nl", "marcelhalma", "roosvonk", "wbhoekstra", "stasfb", "karlijnkuijpers", "veradalm", "radiokootwijkse", "lemvet", "rikhjharmsen", "marcellefnv", "shwood", "jonathan_michie", "faizaoulahsen", "despeld", "guidehouseesi", "traumahelimmt", "olavaamlidsyver", "liekemarsman", "oriperr", "phvmulligen", "jannekevdh", "ed_crooks", "enroctoob", "ruterbas", "jimcust", "digitaltrends", "talithakoek", "dorritdejong", "pauledawson", "tweeting_ilse", "moiraforbes", "cooperhefner", "9spokes", "sensanders", "lagarde", "energiecomm", "bnr", "rtlz", "bbcnews", "fd_energie", "netbeheernl", "energiebusiness", "energienieuws", "energie_plus", "remcodb", "energeia_nieuws", "wouterhylkema", "rogervanboxtel", "straverfrank", "f_mols", "ruudpet", "pauldebeerzwd", "klimaatcoalitie", "antoniopescape", "ainebelton", "soerenellebaek", "derekcressman", "theellenshow", "montesquieuinst", "nunl_politiek", "jefwintermans", "david_energeia", "ulbespaans", "glzwolle", "amerkies", "lj_visser", "basrood", "gliminachakor", "nazimagl024", "moyeecoffee", "wvdwiele", "siriouslysusan", "tjeerdd66", "robbertvdberg1", "shivaune", "jakeliddell", "gonulhettema", "rathenaunl", "pdekoning", "henk_overbeek", "joachimdevos", "pluttikhuis", "edwinvanderaa76", "cryfke", "berentsenlau", "groenecourant", "iamsambee", "wilmakieskamp", "scottsantens", "else4wbdenhaag", "friendsmichelle", "adam_tooze", "de_vkw", "jan_middendorp", "cnijkerken", "foortvanoosten", "devriesjoost", "frankhendrickx", "rietbergen", "jeroenstans", "martijndegreve", "klimaatagenda", "lisewitteman", "thijsniemant", "danielkoerhuis", "mvonmartels", "zelyassini", "mvrooijen", "dilanyesilgoz", "petradegroene", "ing_news", "harriettiemens", "cammipham", "biedermanrob", "tomlouwerse", "bremermaarten", "emsent", "fransvdrimmelen", "lammertvanraan", "miekevandervalk", "amelia_womack", "annettevansoest", "arneweverling", "verwaayen", "energieetalage", "mgpander", "ewarren", "senwarren", "drjillstein", "marinusverweij", "alexanderbakker", "droogheva", "gemeente", "kristofcalvo", "wassenbergfrank", "zembla", "klimaatbeleid", "vision23", "carlijnevos", "spclsilvolde", "makkieonline", "laurapunt", "marjobrouns", "karenvdeinden", "brechtjep", "evertjankoning", "zita_pels", "wilkinsongraeme", "rgovers", "rasmusandresen", "jackphan", "fannicanelles", "jamesfraney", "rogervleugels", "thiddema", "mathildestreef1", "danielltweet", "moiravdputt", "jeroenson", "nielska", "groenezaken", "jornwlucas", "bnrzaken", "riacats", "digitalesector", "interstandards", "edubbeling", "glgouda", "alwinhietbrink", "joriendelege", "eijwoudt", "joukedevries", "thomasvanderes", "lucvanraaij", "scohenjehoram", "schulteben", "wrubens", "stemmingmakerij", "groenlinkszld", "fightinequality", "rloppenheimer", "haydarerol", "tomkniesmeijer", "wewyk", "rutgervdd", "jortkelder", "janhenk_verburg", "gijsrademaker", "amecboard", "laurievdburg", "tnieuwenhuijzen", "saskia75", "lseforbusiness", "groenlinks026", "miekelvdzande", "arthureijs", "claravanhaaften", "willemijnse", "femkegroothuis", "glgroningen", "edgarvanleest", "leenders82", "martijnvdek", "jasmijn_", "gertjanvanschoo", "douwedewinder", "_hagar", "judelief", "ricodb", "lucasbrinkhuis", "groenlinksdh", "renevvanengelen", "gl_drechtsteden", "groenlinks055", "eddiekooij", "jasperblom_eu", "ottevangercees", "tschbeek", "harmdeoude", "kirstenregtop", "janboehm", "arjenlubach", "repunderwoodsc", "esthervrijswijk", "amsterdamdjj", "verkiezing17_dh", "alextobin", "gl_amstelveen", "politwoopsnl", "boreesteve", "jeroenvdommelen", "debroervanroos", "sobore", "sybren_deuzeman", "verywimp", "nytimescohen", "thecookscook", "frankkool1", "roguepotusstaff", "lylemuns", "rudilast", "bootvlucht", "peterdewaard", "adviesraadwti", "groenlinkser", "vepi", "klimaatreacties", "jaapstronks", "enricoverga", "anp_parlement", "myrtezonderh", "lonnyrapallowed", "drostjasper", "rsmits51", "maartenvleeuwen", "channeldraw", "cnv_internat", "dakloos", "wouterdewinther", "roosvermeij", "sebastian_kull", "marionvdkleij", "thijsweistra", "hoventom", "iampliny", "arnouijlenhoet", "dzjem", "buurkracht", "randygasper", "koensteeman", "jeffreyhayzlett", "jos_olsthoorn", "martinbosma_pvv", "glprovgroningen", "dvanbergen", "eduard_schmidt", "martinkortekaas", "groenlinks020", "groenejansen", "timdekroon", "roselaers", "berniesanders", "karinvangilst", "realdonaldtrump", "janterlouw", "spnl", "pvda", "nytpolitics", "parool", "2ekamertweets", "sophie_zukini", "tomwgvdmeer", "lottejeursen", "metro", "eenvandaag", "nieuwsuur", "adnl", "telegraaf", "stellingwerf85", "uschischreiber", "datagraver", "patrickajansen", "estherouwehand", "ruudvangisteren", "fokkesukke", "wallcpa", "selcukozturknl", "sylvanasimons", "f_azarkan", "tunahankuzu", "cvanbrenk", "leoniesazias", "henkkrol", "remcovvd", "andrebosman", "erikziengs", "ockjetellegen", "arnorutte", "aukjedevries", "a_mulder", "pduisenberg", "bentebecker", "bvantwout", "helmalodders", "malikazmani", "barbara_visser1", "tamaravanark", "halbezijlstra", "zijlstra_vvd", "donceder", "eppobruins", "carladikfaber", "carolaschouten", "erikronnes", "martijnvhelvert", "mustafaamhaouch", "michelrog", "chrisvandam070", "annekuik", "jacogeurts", "harryvdmolen", "renepetersoss", "monakeijzer", "antjediertens", "rensraemakers", "achrafglobal", "salimabelhaj", "jessicavaneijs", "robjetten", "svanweyenberg", "paul_van_meenen", "vera_bergkamp", "ivanengelshoven", "jaspervandijksp", "maartenhijink", "cemlacin", "bartvankent", "sandrabeckerman", "jeroenrecourt", "eminebozkurt", "keklikyucel", "richardmoti", "jokedekock", "wmoorlag", "dijkvangijs", "marithvolp", "judithbokhove", "henkkeuning", "johnknappers", "mattiasgl", "ufukkahya", "miekevdvegt", "paulvermast", "wbgroenlinks", "laurenslubbers", "zeeger", "maxvangeuns", "iirisbos", "allochtonie", "coalitiemeter", "alexander_betts", "jeskips", "hildeniezen", "gl_assen", "berendjanjoris", "summerkost", "mirjamwijnja", "p_born", "paulavaneerden", "paulhelsloot", "chris_uitabcou", "pimvandendool", "suuswill", "klaasstrooker", "matthijssikkes", "inenagelmaeker", "hengeveldmaria", "allertham", "secondhomemondi", "debaerd", "desmetels", "tijmmm", "janmuijtjens", "heinalbeda", "marijnissenl", "wouterwitteveen", "margreetdeboer", "mickellangeveld", "esterfaassen", "buitenhoftv", "arjenbaars", "giedojansen", "nipped", "tomvdnn", "groenlinksrdam", "jade_vd_linden", "daisydelaat", "warrenwhitlock", "barttrouw", "ruyssenaarsjan", "remkodepaus", "marklouwrier", "b_changenl", "minitrue_nl", "celalaltuntas1", "maxtollenaar", "groenlinkscastr", "helencmarketing", "irene156", "koosspanjer", "tonwolf31", "rikthijs", "ron_013", "vincentkoerse", "dilekodabasi", "roccopiers", "janetduursma", "arnobonte", "mayavirg", "cedericduboisch", "simon_miske", "gebertgroenlink", "cathelijnecb", "isabellediks", "wimjanrenkema", "laurabromet", "zihniozdil", "emvdg", "fem015", "dewaremerijn", "patrickrijke", "noorblokhuis", "boelensl", "keizertrajanus", "janneke_eigeman", "riteco", "hofstelotte", "armaganonder", "dheuvelmans1", "glrenkum", "pieter_kroon", "jblokzijl", "monicafalck", "bertsonneveld", "nielsjeurink", "robertkleiburg", "pieter_kos", "eva_huson", "smitsstef", "pauliengankema", "bosmanmariet", "ankebuur", "larsduursma", "peter26061980", "ceesjanpen", "thomassluijk", "hugohoes", "joostreus", "rensvl", "jmschollaardt", "aadzuid", "isabellewoerkom", "axelboomgaars", "waltervanpeijpe", "etiennegoud", "harminos", "nickyvwanrooij", "yvettehofman", "hildapasschier", "euractiv", "erinmoon72", "trouwgroen", "youaremankind", "groenlinks030", "fnvmondiaal", "floorbremer", "ealawsociety", "huibvanessen", "reporterphoenix", "robinjpowell", "fairwork_nu", "sandrahclaassen", "thomas_fabrie", "tssstweets", "pgkroeger", "bradzarnett", "ictafrica1", "fabiodemasi", "jangruiters", "coenvdveer", "cynthialive", "theathwareing", "jasonsquiressm", "pierremoscovici", "stephen_quest", "hasbakker", "teresafogelberg", "climatehawk1", "bizbuzzamerica", "kenradio", "jrigterink", "pablorodas", "duurzaamenergie", "politicoeurope", "simeonkerr", "kevinhyland63", "clarasteventh", "kwestiesntr", "keeszevenbergen", "joycekortlandt", "kirstenvdhul", "amyalaporte", "joycesylvester", "terrebelius", "pamelafalk", "paul1kirby", "ournewecon", "johntrumanwolfe", "jojanneke", "menno_tamminga", "josh_cee2", "nonfungibleutd", "rvantwillert", "eric_vanpraag", "kuipersjasper", "gduval_perso", "j_dejong2", "wijnand_dde", "basweegberg", "spencerthink", "nevinozutok", "adamitv", "dannymekic", "avinashbhikhie", "peterkwint", "leesclubvalles", "ejn_greencareer", "agoodall4", "voicetweetz", "hrs07697658", "mariandraaisma", "mvgerhardt", "lisa_vd_velden", "imsahra", "newclimateecon", "landrightsnow", "angeliquevant", "andybrown1_", "femkemerel", "kapteijns", "ellenwalraven", "transavia", "agkoenders", "sustainable2050", "wimaalbers", "michelleobama", "iamaecreator", "dinapomeranz", "vitolaterza09", "wikileaks", "studiodebates", "laytarr", "tradenewscentre", "puur", "darrinsalt", "michielminded", "janvdmeer", "wbg_ida", "climatemessages", "vkgijs", "wbg_climate", "cnn", "jeremycorbyn", "learnwithimpact", "venture", "anticorruption", "ti_eu", "gooijer_pieter", "twpetra530", "artisticcrypto", "darrenkavinoky", "bjornkuil", "u_s_principles", "johon_gutierrez", "philipdeww", "henkvanhoutum", "gaviseth", "leonijanssen", "www11be", "frisofennema", "bartvanbruggen", "marcolivierherm", "justintrudeau", "biznessreporter", "annefleurdd", "carolinaurrego", "4stayinghealthy", "oxfamnovib", "tabledebates", "bewaredog1", "teijeir", "cayenneapps", "cagednreality", "nonprofresearch", "m_marope", "maxcroser", "webcare_vk", "jrrjbos", "peloblancophoto", "storyhinckley", "annemariayritys", "cliffordious", "mypowertalk", "jetar9", "axelkoster", "dbgyorgy", "youngcriticsnl", "teung", "faizashaheen", "tamraraven", "euinmyregion", "axelarnbak", "crowdpac", "world_weekly", "robberends", "offsetnetwork", "sybrenkooistra", "pierrevanhedel", "nporadio1", "zaheer_bux", "storylabai", "raultiru", "michieldijkman", "fahmidaiqbal", "haticedenizavci", "markjansen10", "christiaanvos64", "matthijs85", "openstateeu", "larssorensen", "postma_jeroen", "wesselnos", "lambertgrijns", "trouw", "siegel_michael", "mssophiaakram", "bbohilke", "sergireboredo", "brytlytdb", "joorthuizen", "pascal1505", "brbrasseur", "noorlanderarjan", "laurensubbink", "mikew4id", "sandra_vdlee", "teesarab", "duurzamestudent", "oxfamibis", "tponl", "bothsocial", "forumforag", "sylviaeken", "_metafizik", "gppac", "humanrtsv", "france24_en", "aswoodie", "tjeerdhobma", "campanalemark", "carbonbubble", "mudjeansnl", "diederiktencate", "sabine_ilc", "dannywijnhoud", "desocieteitntr", "marcelgreensoap", "richardcarman", "enesciceknl", "politics_pr", "dr_jim1", "koosdebruijn", "drsarahb", "aropmeer", "msftsmartcities", "planetary_sec", "hebbediekiek", "egbertkalse", "luciaweihe", "alexanderkoene", "murraynewlands", "joreri508", "_rajpatel", "eduardnazarski", "orsini70", "sport360arabiya", "vanliempt1op1", "mrmake_hersmile", "guardian", "a_campolina", "mjhietkamp", "laylasalamoun", "meredithcarfen", "ptrdbr", "middleeasteye", "femmydejong", "craigaatkinson", "ecocidelaw", "fairsay", "mlodewijkx", "followthis2015", "climatemorgan", "readthisthing_", "mackelenberghd", "ics_centre", "leanconnection", "onlinegallery8", "hana_abukar", "marleeng", "kamiel79", "roboverwater", "donaldpols", "marlijnd", "macharoesink", "tjerkbos", "cllrtomhayes", "ariseshscribe", "sandragallina", "hanslak", "rbrutti", "hsquared_studio", "twisty_traveler", "terrywhalin", "allriot_tshirts", "ratcliff_anna", "angelacapraru", "goranhenriks", "budgetdude", "ejnetwork", "comblibindex", "unocha", "oxfamgbpolicy", "brainssummits", "bvpaassen", "greensandco2", "e15initiative", "realdigitalmkt", "hannahmcneish", "hulyadagdeviren", "theadamhowell", "vijaybdixit", "tomas_brambora", "wcampingheeg", "emilfretheim", "eightiesrocked", "djangowinedog", "_atanas_", "gargieahmad", "olliten", "francoisevanni", "bizhumanrights", "12freelancenl", "elledubg", "peterkanne1", "eu_commission", "civilsocietyuk", "ngos4justice", "opengovpart", "freedomhouse", "civicusalliance", "insideclimate", "sierraclub", "thestudyofwar", "theatlantic", "johnkerry", "csis", "unhumanrights", "undesasocial", "mwbloem", "obinutuzumab", "zyafet", "joshuapriore", "itszavagez", "commun_it", "david_yarrow", "sara_cowan", "jessicawheelock", "ck_knebel", "hoberstorferk", "valuesstudies", "depitchfabriek", "faberpetra", "cecile_pilot", "ericvrijsen", "lailaaitbaali", "mkutney", "kimallenpeng", "sak_nepal", "schaatsennl", "dacia_nl", "jorientermors", "hutma", "comwborders", "genaud_solisa", "yournalismnl", "janpaulvansoest", "tuvarb", "aquaforall", "katrinanation", "tajiel_urioh", "stephanygj", "renanetjes", "roelschrein", "syriacivildef", "m_meijer", "mariannezw", "tristanylovell", "fuzeus", "boftayimam", "wnlhaagselobby", "mikehudema", "anticorruptintl", "idegoede", "wdekanter", "tlightly1", "1971dsgn", "mmc", "in1week", "van_vulpen", "rociogayarre", "jongegeesten", "ard_bakker", "marjonbachra", "navverheul", "cnvvakmensen", "nonverbaaltje", "thomaskeister", "scheffer1paul", "switchbackwelln", "cristobalaviles", "paul_maes", "socialmovetech", "wileikelboom", "civilsocietypol", "jerrybeller1", "willemlageweg", "bramspoort", "hawk_rising", "antaldewaij", "eurotecenviro", "carolinehurford", "floortjeklijn", "josemoriano_", "rienekekoning", "owlpb", "cfadc", "liescraeynest", "samooner", "kc_honduras", "sanlihollandali", "annekrogiversen", "chadlhymas", "samsilverstein", "tblackpetersen", "mthathisipho", "kennethdavid", "totjoelker", "haydentiff", "ilse_db", "environews", "marymunnik", "marius_mpoweru", "transform_h2020", "ppeorg", "deginvest_int", "lajongenelen", "commonstake", "melissafleming", "unicefsocpolicy", "stewface", "fier_nl", "stevendejong", "jgleizes", "roelsnelder", "ecowanderlust", "famflix", "uppitybum", "jaapkeeren", "dpoelen", "sharenetnl", "roodlicht", "ffatumo", "cvdullemen", "hjochemsen", "planetstraight", "benparker140", "anthonymiyazaki", "mdgmonitor", "bigpublisher", "continent_noir", "glowsocialmedia", "oximitymigrants", "eglobalmenu", "kiraonclimate", "beerforums", "makilane", "brewstuds", "maiolsanauja", "hoebink_paul", "msuzman", "airismartinez", "jorritkamminga", "georgehatcher", "marianneqps", "kinderenergy", "qtsentrepreneur", "duckduckpanda", "sheq2502", "lid1108", "awalender", "tribespeople", "jesper_munkholm", "kampetero", "oxfamcampaigns", "unsdsn", "lennimontiel", "womenfoodclimat", "dynamicagca", "andreasrades", "pureenergienl", "maradange", "danielnewman", "lnspiredtweets", "bbctrending", "safetyaccord", "cbankumuhari", "buzzfeed", "jovany_villamar", "oecdtax", "mobilefactorynl", "urgenda", "samsam_magazine", "trove", "bercangunel", "roziebreen", "africancir", "annekwakkenbos", "koendetavernier", "michaelrolph", "thierry_dufay", "ran", "toltheten", "eelcofortuijn", "officialmltr", "t_labrujere", "peterebert", "jobsearcheu", "foodnutsecurity", "lynnserafinn", "zoedejean", "betteke", "tijdvooreten", "vluchtwelkom", "ohoid198", "miadschaem", "londil", "ulrichjvv", "elliptigohuur", "rv_hagen", "patt_foundation", "fionadove", "veerleslegers", "ifdctraining", "diepbak", "lilyslynch", "lifelanddignity", "bkb_nl", "seed_sustdev", "oxfamhexham", "socrata", "mkbcongres", "n4miorg", "ttpdp", "csodisruption", "hille_takken", "jamesbulman1", "vanita_su", "karimi_karen", "reinierspruit", "jamescopnall", "adrianvaniersel", "squirestim", "ignaciomls", "tomdangora", "clydebrothers", "seminsky", "tb_kristal", "adamparkhomenko", "tommikkers", "mombergrtt", "hwpositive", "chelseaclinton", "revolverphoto", "uechigbu", "bauplan_images", "bupardeeschool", "superegoworld", "douwebuzeman", "plasticbankhti", "circularecology", "kristinedugan", "lj_spengler", "thijsbroer", "fuller_future", "arievandenbrand", "fairtraderenkum", "zak_bond", "marena_b", "rolfharbers", "sebafarmborough", "cgmooreauthor", "msjenko", "banktrack", "shantyfrancis", "teekayzim", "bresearchlabs", "sabinacuratolo", "mijnonlineid", "assaadrazzouk", "zamba_me", "keithslack1", "sam__vdp", "zubairsay", "portermcconnell", "eval_impact", "lukealexgibson", "juliethekkudan", "alexmolteno", "maraluisaromer1", "thegoodshopping", "dtdchange", "monsitaris", "jeroengerlag", "poovenmoodley", "moniqueneyzen", "hilhorst_thea", "ajfiore", "willfitzgibbon", "dcdd_nl", "oneinafrica", "climatereality", "aboutthinkers", "lovelondon2013", "girlsmindqts", "afradeleeuw", "encludeholding", "fmo_development", "upsides", "isabelledel", "who_urbanhealth", "paulpolman", "bureaumvo", "hermanb", "eric_reading", "ifdcglobal", "returningassets", "vaqarahmed", "vaneshaseechurn", "corruption_sa", "c_natacha", "alastairbreward", "alexandreseron", "mvo_nl", "hetgroenebrein", "vbdo", "mvdoorninck", "ethicsedinburgh", "klimaatzuster", "profjeroenbergh", "johnpodesta", "psaintamans", "aimee_brown_", "freek_md", "emmanueligunza", "dft", "alfonslopeztena", "adamsrecruit", "deeep_ache", "chrhallum", "sanjeevprd", "zimbabwewatch", "gautamraju", "nie_chris", "hennygerner", "trevruddockjohn", "nilimajumder", "digilieke", "joelvoordewind", "adymusgrave", "philippeburger", "savechildrennl", "maxinetillij", "ophetstrand_nl", "drpatrickwebb", "stveiligvoedsel", "jasperine_md", "npex", "thomasdehoop1", "alexiaskok", "shaunfrankson", "fantwit", "rwinw", "ediskoe", "vbagaaya", "omdenken", "stiangeerts", "jjgogonzalez", "mikeschreiner", "rikgrashoff", "rylegerard", "frankdaamen", "seifmagango", "poliwork", "fionazwart", "danielmulder", "ian_fraser", "frankdonkers", "oxfaminke", "danmackenzie0", "karinhornstra", "brianmarketing", "cleanupnigeria", "recyclepointsng", "chiomaukonu", "helenatweeets", "joaoscarpelini", "rptw", "tchonaconstant", "mathiaswasik", "ga4tj", "potus44", "potus45", "robvandestar", "twludwig", "lizaluesink", "marijeploeg", "cobicalyx", "sieberandreas", "asimbajwaispr", "_pamanders", "pierce_smythe", "the_earthworks", "guitymohebbi", "ankiedols", "jacobinesdj", "panmalaga", "martiendas", "jolandavginkel", "davene_wenborn", "seetheroses", "port4growth", "nickvenna", "lau_vermeulen", "hetgaatmijomjou", "kroreporter", "eziosavasta", "mandeep_dh", "ontariogreens", "ludobok", "martin_steinman", "wrobertsfood", "tomas_vanheste", "chicagodesign", "adamsarwar", "humanityxr", "g_bertoncello", "emil_linnet", "gbickerton398", "unuwider", "finnsangle", "awid", "practicalaction", "wrrthinktank", "marc_brouwer", "mvantklooster", "marijkedeleu", "nicolaasderegt", "jfgvanbommel", "includeplatform", "joosttaverne", "wfdenood", "nicolasvercken", "rreppaustralia", "themekongclub", "sylvia_yf", "open_aid_data", "standardoftrust", "manonstravens", "attacaustria", "lauryhaytayan", "sarahdanderson1", "sallycopley", "shingayi_manske", "t_dunmore", "debaak", "brandpunt_plus", "lucamig", "bokoharamwatch", "yanisvaroufakis", "marcwegerif", "lanampayne", "rooseveltinst", "jorisvdkerkhof", "atsindex", "meyerron", "larskoch", "action2015", "actiontime", "geraldkutney", "davidch27992090", "nadiabouras", "rsavelberg", "fgeerdink", "forbes", "kirkjaco", "krijnschramade", "michelmaietta", "daynareggero", "dutchbluebv", "letlifehappen", "ericlangalakhe", "tonysangle", "rbrooks45", "catherineolier", "sven_giegold", "andreasjonkers", "kajsaollongren", "rf_hfc", "amnestynl", "nef", "publicintegrity", "assodesire", "pisaniferry", "media_guy22", "pltbros", "animaksuk", "astad_eu", "hpvanderwoude", "obk", "climatecentral", "odiclimate", "fareedzakaria", "tombowk", "btahziblie", "alienkeramaker", "leray_r", "jimclarken", "mholtrop", "mkemple", "globalsherpa", "gijs_de_vries", "yvonnehofs", "margosmit1", "hermanvg", "ideruyter", "spectatorindex", "mitgc_cm", "martinwolf_", "thedesmondtutu", "marikendj", "janvierchando", "rescueme13", "schuldensuehner", "basboelh", "rianne__84", "arlinde_plomp", "rschuddeboom", "lvandenassum", "hestersomsen", "usernames9000", "bbuizer", "sfoodsupply", "womeninc", "yorian", "margahoek", "energieoverheid", "_tessel", "michaelwhudson", "evduin", "igg_nl", "4michaelwings", "tjip", "selwynmoons", "collegeclubnl", "pinewsglobal", "jornmatena", "ericsmaling", "blogaction_", "tinatinde", "naomiprof", "jmmuriu", "apaardekooper", "siphokings", "sdgactivist", "stephen_yeboah", "climdevafrica", "isabellalovin", "margotwallstrom", "nlincdi", "oxfamsverige", "angelazutavern", "randymartens", "emmawatson", "european_views", "sanne_tielemans", "diakhoumbag", "europeanenvfnd", "cjochnick", "tompaulson", "meschuurman", "maketaxfair", "sociomedias", "sadetkarabulut", "rachel_brabbins", "ecocraigjones", "linaholguin", "angelacorbalan", "oxfambe", "oxfaminpakistan", "oxfamscotland", "oxfamfrance", "oxfamnz", "oxfamgbpress", "insideoutbrand", "shaleclimate", "vngalasso", "martingilbraith", "kimputters", "msalimu", "brunogdavid", "walrathis", "rinzebroekema", "wyeates", "evajonassen", "amitvatsyayan", "centeronbudget", "nrc_egeland", "andynortondev", "chinafile", "dev_progress", "martijnharlaar", "nytben", "samdagher", "rudoren", "abarnardnyt", "borzou", "faosocioecon", "paulhbeckwith", "oscarjpearson", "londoneconomic", "arwamhanna", "suying_lai", "saskiasassen", "ggereedschap", "brooklanac", "barbaraabos", "taxjusticeafric", "carolmliao", "dvdorresteijn", "margotwit", "ball_sandra", "mattgrainger0", "chris_mungai", "wageningenint", "magnus_sculptor", "gabriel_zucman", "cultuurpers", "coenteulings", "econjared", "ruerdruben", "hellahueck", "gerdovang", "laurensivens", "ldaalder", "harriettolputt", "ellengustafson", "ericchrsmit", "timharford", "mattbruenig", "derksauer", "inclusivecap", "africawoodgrow", "digipubs__", "ftm_nl", "richardvankray", "mamboe29", "grodan", "grodan_nl", "pdegrauwe", "kevin_watkins_", "k_roovers", "kateraworth", "patagorda", "pikettybot", "spotgirl", "keesboonman", "davidcorndc", "mariettepnnrts", "adelheidroosen", "hugovdsteen", "lotteleicht1", "daphnedertien", "marjaruigrok", "eloisetodd", "d_bangma", "d66amsterdam", "zustenebol", "aniruddhabrahma", "marcchavannes", "tim_e_gore", "edvotes", "vandammeedu", "keesberghuis", "pieterkleinntr", "tomjanmeeus", "joostoranje", "mstellinga", "dorthe_s", "fowlerpenny", "onenederland", "femkeroosma", "paulemetz", "bruegel_org", "beoliverav", "inequalitybrief", "changeinctoday", "josephestiglitz", "euobs", "willemvandeput", "interactionorg", "jorisoldenziel", "thomaserdbrink", "fernandezamster", "sjoerddendaas", "ruudvandenhurk", "matthijn", "foreignstrategy", "gotonictonyo", "fbonaglia", "jeffs_journey", "sonykapoor", "hansariens1", "hjdb", "intltaxreview", "hansberkhuizen", "lvnistelrooij", "wrrongelijkheid", "c_johnes", "mccharveriat", "nicolasmombrial", "eduardschaepman", "jvdevlieger", "andrehaspels", "ascleiden", "jpaternotte", "deliver2030", "jerrysycommerce", "annemariekas", "restorm", "fingerfootball", "michaelkolson", "tom_burke_47", "aprilranshuysen", "europarl_nl", "butchermartin", "cafreeland", "johngithongo", "marnixsegers", "jamesjohnsonchr", "oecd_centre", "jeanvanwetter", "nigel_chapman_", "urgentem", "sjlillywhite", "kasthomas", "rougewoman", "sominisengupta", "amazing_maps", "wonkmonk_", "rcjmvanschreven", "africaprogress", "pmanda_2015", "moiravdputt_x", "andreadijkstra", "incrediblemaps", "rooiehein", "amprog", "unecosoc", "shawnupchurch", "aid_leap", "crowdenergyorg", "0xxxx1ixxxxxxx0", "illicitflows", "robbibarbieri", "laurajansen", "verhoeftim", "rivefuentes", "oxfamjerusalem", "wnicholasgomes", "deschuttero", "pkpraveen8", "xandervdwulp", "cjvandenbroek", "bjornkhaugland", "vera_nassau", "kottechantal", "parrav", "josvandrogen", "eriksolheim", "luclampriere", "jos_douma", "stability_fund", "leenboer", "fairwearak", "hansdocter", "marceldevink", "koendavidse", "leonicuelenaere", "compendium_clo", "avinash_1_kumar", "j_roodenburg", "shonuffynft", "harmanintoronto", "rooswouters", "bartvanzwieten", "brigittetweet", "shandarenee__", "greenintentions", "mjgbrand1972", "carmenttong", "tamiragunzburg", "advocaat_ps", "oxfameu", "giuseppevdhelm", "endpoverty2030", "epinnl", "viewfromthecave", "jimharris", "suitpossum", "loripetryk", "carolinekende", "billclinton", "burke_jason", "ggatehouse", "fpa1918", "paulvanliempt", "faoknowledge", "louisevandeth", "piaahrenkilde", "uninwashington", "simonefilippini", "nlambamaputo", "nlinmexico", "mdekwaasteniet", "verheul_jeroen", "fonsstoelinga", "jolkeoppewal", "eddymiddeldorp", "aggelenjos", "hanpeterssa", "noevanhulst", "wjpgeerts", "beatentusscher", "keesrade", "laurenswesthoff", "ahennekens", "joostreintjes", "kvanoosterom", "carystaylor", "inequalitiesblg", "marijke_vos", "donaldkaberuka", "pcanfin", "svhoorn", "janeikelboom", "annemiekenijhof", "fms_foundation", "jacoduplessisza", "africasacountry", "oxfaminsaf", "taxjusticenet", "justinegreening", "propublica", "margrietvonno", "true_price", "naturerunswild", "dooleykate", "economischedipl", "renevanhell", "chrrebergen", "gogreeneveryday", "o_rutazibwa", "seawildearth", "350", "mckenziecnn", "cblatts", "fmgomad", "hillaryclinton", "sdmattpotter", "brankomilan", "davidklingen", "jhmommers", "nishaagrawal007", "davidcastaindes", "mbeukeboom", "maaikegulden", "helenmets", "yamashitanoid", "leefomgeving", "teakisi", "theladyknight", "icijorg", "mapxxs", "mashanubian", "nicopraat", "corinneellemeet", "jenny_ricks", "energiepodium", "sebfourmy", "smitleo", "benaffleck", "mark_goldring1", "j_schokker", "coachwim", "africanbrains", "nkaizilege", "wytske_postma", "johannesguetl", "nickshaxson", "socbxl", "henkwillemsmits", "jeffreyuitnl", "tninstitute", "unilever", "platformoio", "ikennaazuike", "nwpls", "frankheem", "richardjwood", "mcrispinmiller", "sandralutchman1", "kanteldenker", "adam13576", "danielle_h_be", "will_henley", "judy_beals", "asiarisingtv", "ganaderiayagro", "oxfam", "mattsteinglass", "hakhverdian", "globalcompact", "willems_leon", "michelvanzessen", "mannfrednikolai", "uffelenjohn", "md_jong_", "11groupltd", "alvinmosioma", "richardjmurphy", "pietheinxxs", "cocoaconnect", "jessedrucker", "decorrespondent", "marionderckx", "climategroup", "conflict_world", "taxjustice", "csisafrica", "jongambrellap", "lindamiriam", "martnewillekens", "corriejonkers", "mknuijsting", "joriswijnhoven", "bondngo", "fransweisglas", "politico", "yvodeboer", "siddyjobe", "bryantmcgill", "wilcoboom", "zzpaov", "archieaid", "bobpickard", "minkonto", "iied", "corinnekeijzer", "acumen", "marionnestle", "nathalieolij", "galbraithjeremy", "superernie", "247hrm", "frankmechielsen", "esther_lammers", "ictsd_bridges", "alex_verbeek", "un_spokesperson", "pbloomer", "fteconomics", "jonivandesand", "machteldanna", "wverdoold", "habib_malik", "secr_commissie", "kgeorgieva", "xfranco", "pdiscoveryuk", "smndkk", "wilfredbruin", "smaxbrown", "bethfoodag", "firetail", "frederiekeh", "mcarthur", "rjonesbos", "reliefweb", "africarenewal", "africaresearch", "arnoldkarskens", "rvo_nederland", "africagathering", "chrisbuijink", "nancymbirdsall", "theafricareport", "ijm", "ferrymingelen", "reingelten", "sytskejellema", "sustainmomentum", "janvos", "jaazcona", "conradhackett", "annaschoemakers", "harmbotje", "iioannoulbs", "joepenney", "_rubeneg", "broedert", "euinnl", "ilo", "foodtank", "sharanburrow", "sanrottenberg", "pjenningsuni", "kevinado03", "flotus44", "flotus45", "stratosathens", "joshrogin", "bertvansteeg", "winnie_byanyima", "susfoodtrust", "fasol", "bertjongert", "fredvdkraaij", "gihanztweetz", "worldbankafrica", "rudolfdereiger", "iicd", "natuurenmilieu", "faoeagriculture", "africatechie", "mjwoudstra", "humanrightswww", "annemiektemming", "_dinomelaye", "yvetteveechoud", "knwanze", "herman_wijffels", "reutersafrica", "sanderdekker", "paul_bijleveld", "cfigueres", "marcvanderham", "sullyserena", "cjcorbett1", "newhumanitarian", "acc_ict", "pvangompel", "doylebytes", "connolma", "ingridrobeyns", "climateclg", "worldgranny", "conchitavrooij", "ikerkvliet", "miekespaans", "tadeksolarz", "treesforall", "daalmans", "henknijboer", "globalgoalsun", "nelsonmandela", "fp2p", "minbz", "wol", "liekelamb", "smithinamerica", "akhilak", "stefanbril", "annafeuchtwang", "jasonkstearns", "vitolfiel", "annamac33", "janrotmans", "actionaid_nl", "gerhardschuil", "marjoleinstok", "gertjansegers", "iwillsoiam", "markweston19", "marlousverbeek", "mariettasmid", "stopwebbullying", "humanitaaffairs", "mrenda", "monetarysystem1", "ajarvis8", "ninatellegen", "dennismel", "aberkvens", "chamwamba", "bulentisik1121", "dbonis", "camild", "agnesmuldercda", "jacquelinelampe", "frankahummels", "fenkeelskamp", "evertjanbrouwer", "devex", "ekleinreesink", "david_mcnair", "annpettifor", "eurocrat", "thewhyfound", "motherjones", "wimklei", "woipnl1", "grazianodasilva", "sladesuiter", "globalizationnw", "dorcashulp", "janhoedeman", "markvanluyk", "maritmaij", "michielservaes", "cidse", "aynte", "tomvandenberg", "guyverhofstadt", "helenahulsman", "willemijnland", "annedeblok", "denaamafdeling", "dougsaunders", "swsjoerdsma", "wijzijnmeo", "anjavde", "fairtradestore", "janwillemwits", "martinzuithof", "koenvoskuil", "femstr", "jeroenpauw", "bjinsedankert", "asiapacificview", "social_skill", "judejudoh", "elsascholte", "mpoppel", "jeroenloots", "mikeorzen", "remkotheulings", "filmkus", "norton_tim", "willemwiskerke", "unescap", "bertblase", "sscgconsulting", "theaef", "krieks_media", "jellebc", "ruthpeetoom", "nynkedezoeten", "mvroomans", "amnesty", "sybrandbuma", "stepvaessen", "keesgroeneveld3", "julietoneill", "jfbroek", "1hschulte", "robertfox_", "africareport1", "nextstarfish", "crownmedia", "zzpnetwerknl", "wbg_poverty", "janvandevenis", "secularundergro", "raouldupre", "larawhyte", "anpperssupport", "radio7africa", "jorisnos", "bramvermeul", "tamaralevine", "hannodriesser", "verheywouter", "omathivha", "renzodeurloo", "bramvanojikgl", "ids_uk", "keesvee", "edpomfret", "prdvfoundation", "svveldhoven", "daniel_puglisi", "mryeswecan", "tweetabrics", "dbatcheck", "vluchtelingwerk", "cobbo3", "folkertoosting", "pseitzinger", "greencode_nl", "jannodemanno", "moniquevanes", "marcogroot67", "lisawesterveld", "humbertotan", "brittabolt", "bedrijfsplannen", "dpaulobrien", "amitbadal", "lexhoogduin", "dance4lifenl", "tomaswyns", "cohedegaard", "laradebrito", "nopduys", "ingriddecaluwe", "kdiepeveen", "margotvdstap", "pieterheerma", "prosyn", "pla_voluntario", "stevept", "chantalgak", "iphoneipadfans", "trendstonehomes", "jonahlupton", "landcoalition", "attilatavasszy", "nolabelsorg", "charlottelafort", "bramwits", "wereldpodium", "afrodig", "tom_schoen", "lizfordguardian", "basvanderveen", "janjosephstok", "ifcafrica", "africareview", "wimdebie", "robsaunders74", "ppslikker", "unpeacekeeping", "eshavanderhulst", "kikischippers", "dave_ensberg", "henkpijlman", "bijlbas", "sjschoppert", "olfertjan", "bartpierik", "rmrlldr", "ahfawzi", "lrmg8", "wellbeing_nl", "timvanlieshout", "hverbeek", "twwieb", "dabnos", "mahirzeynalov", "theovanderlee", "maartenschinkel", "gonzalofanjul", "lucgroot", "bracworld", "open_for_change", "solidaridad_nl", "niawag1", "ritapoppe", "migiel", "olivervanloo", "bopinc", "afuahirsch", "tomkleijnnl", "justinforsyth", "noswaagmeester", "advanoosten", "mittromney", "deviswijzer", "judithverkuil", "ralfbodelier", "dvrichardson", "bibivanginkel", "concord_europe", "tensflexwerk", "nos", "peterreier", "bleenman", "romanbaatenburg", "anoushanzume", "yelletieleman", "vrateau", "ppdejong", "rplasterk", "karinjensma", "hansrosling", "jobjan", "axelveldhuijzen", "mariekenos", "nlenvironagency", "pvdmeersch", "bramgerrits", "rolfwijnstra", "dean_ngo", "cerrj", "bhvned", "frodo1977", "elluina", "jurgenvangessel", "keesbloklandphd", "josettedevroeg", "melaniawomen", "thijsreuten", "reportershub", "m__breedveld", "bulungiuganda", "maartenhajer", "roelof", "eenmoo", "michieldehoog", "de_willem", "anselm_iwundu", "smwonline", "merlijnstoffels", "timoreilly", "annemarijke", "kmmol", "iriskum", "erikvisser", "steeph", "namrepus", "elsbethgruteke", "our_common_food", "peetgron", "worldshopsneek", "cemgo", "vmvd42", "headandbrain", "marijebalt", "haroldnature1st", "chgroenhuijsen", "jeroenvangerven", "marijevisee", "mirnatweet", "benphillips76", "jessicabekker", "reputatiegroep", "rinekevandam", "socimediexp", "seumasmilne", "idfa", "ch_alonso", "france24", "drbobbullard", "kofiannan", "labelgmoscv", "jonjensencnn", "passop", "jeroengunter", "envjustice", "goedgedacht", "khadijaarib", "rjhschepers", "saferworld", "discsomaliland", "egoliafrica", "marlieskaty", "simavinl", "humanityhouse", "janjuf", "sjef3", "iobevaluatie", "wereldsupporter", "iraqesque", "learnhomeopathy", "sandervbennekom", "wereldgasten", "ewoudnysingh", "thesecretlab_nl", "benien1234", "amykoopmanschap", "laurens_degroot", "mcfaul", "partosnl", "richardjspencer", "drkraszynskamd", "helgavkampen", "hedwigbruggeman", "kenroth", "g20rg", "change", "ejstroesatidhem", "iamami_85", "pieterschut", "gefsoutlook", "irunguhoughton", "robinhoodtaxuk", "soci2012", "livingstone2004", "illya66", "paulojohn", "grevanderlee", "melindagates", "sssnappie", "puuruiteten", "henribontenbal", "klimaatverbond", "sx3nl", "somalilandsun", "anitabuzzz", "chicoxperto", "egonvanwees", "akpoliticologie", "kemeijer", "princeclausfund", "aafkevans", "philliponeill", "ecdpm", "hermanstam", "westwingreport", "titialeeuwen", "smandic", "boomerangomics", "heleenweening", "ozziezehner", "brunobrussels", "sfyn_nl", "leodvisser", "astro_andre", "brekendnl", "samuellevie", "mireilleverhoef", "zeinakhodraljaz", "suzanne_gl", "laura_rusu", "hansjmelissen", "renecuperus", "tomfriedman", "ianbirrell", "hansspekman", "reijerzwaan", "economistmeg", "annemariehiland", "peterverhaar", "dick_kalkman", "masiafshar", "flexmind", "peterleuhof", "lapperre", "stefosis", "debortolif", "wiebevdploeg", "tinekeadmiraal", "sjakki", "pieterpeelen", "sywert", "expimportlawyer", "irmavandermade", "humane_rights", "davidstomph", "klimaatplein", "kathelijnhendri", "bradleyjdibble", "ytkempkes", "anneketanneke", "kcollet", "lenegrooten", "myfairobserver", "jorritnuijens", "flowgomel", "lennarthuizing", "powercompany_", "oecdwatch", "beursstier68", "euronext_nl", "brettrelander", "ibtimesuk", "undersquitonet", "frankvanberkum", "noviewfarm", "jorislohman", "mamopanel", "francetim", "kuminaidoo", "monaeltahawy", "mwijne", "remcott", "pipbrant", "gratisleadsnl", "svandam26", "sultanalqassemi", "hrmnieuws", "jojanneke_n", "gulliverconnect", "youwe_global", "frankdebakker", "gerald_vandijk", "doesjkadubbelt", "rogermid", "antaldaniel", "martinplaut", "laurensvhg", "geoffreyyork", "victoireumuhoza", "alexcobham", "anneeke", "olgalouise", "jonathanglennie", "anketijtsma", "margrietswart", "martijndadema", "thenextimag", "karenallenintl", "chrisadamsmkts", "simon_nixon", "marjanminnesma", "jacktsang42", "halagorani", "cchristinefair", "larsonchristina", "graham_baldwin", "fgoria", "abuaardvark", "ozgurtufekci", "naomiaklein", "thisisafricatia", "socialmedia99eu", "drfrancisteeney", "maxlawsontin", "patrickspijkers", "snvworld", "onskinderpardon", "mrjasonray", "judithmadigan", "rensvantilburg", "floorsite", "roeljanssen2go", "peettv", "royovitz", "natemccray", "gerardversluis", "fatihyaabdi", "stukjesinfo", "eelco_npartners", "oneaup", "geertjanw", "martinfaulks", "ecb", "martinvisser", "mathijsbouman", "pholt63", "socialmediasuc6", "rolfschipper", "erikjan", "marksedney", "jeroenklomp", "yfken", "bert_d", "franskoster070", "vrouwenpower", "daphnedewit", "djnieuwenhuisv", "maureenagena", "openeurope", "highestdiscount", "larsros", "ewaldeng", "movietomovement", "natalie_kabul", "hugologtenberg", "prodemos", "subventionbv", "floraarina", "jamespedrick", "hapeeg", "kenyanpundit", "devinder_sharma", "edwardrcarr", "andypsumner", "digdeeph2o", "mirjam_de_rijk", "zoekcomphulp", "worldbank", "markvkollenburg", "lilianvisscher", "shakaverse", "anna_hamersma", "theordradicals", "_basjacobs", "marliesfilbri", "tweetforceone", "paxmarjolein", "del_agua", "edwinmooibroek", "hungerprojectnl", "kncvtbc", "fanrpan", "mauritsgroen", "buzz9janews", "fazzjobs", "anouk_vanb", "thirzamb", "wykesmit", "stephencaggiano", "mvoplatform", "irenetaroni", "csdworldwide", "bellebolle", "stoptbc", "marya1986", "dasnouveauvod", "prosenmoller", "nazmiyeoral", "jellegudden", "eindevelopment", "lotjem", "pietsprengers", "gsdrc", "denniswiersma", "_matthew_price", "iccotweet", "gdndevelopment", "kabelbreukdnb", "kerriejen", "financeasia", "barthoboer", "futurefortified", "soschildrenuk", "giro555", "trommeltweets", "rpsteffens", "wimnoordam", "lvveldhuizen", "ethnicconflict", "svenst", "willekeverwoerd", "faosomalia", "ventura4u_", "eddebeket", "fliptomadrid", "petranysten", "stefanjansen50", "batmobile4ever", "evasmits", "ellyblanksma", "wkoolmees", "ecogoodies", "liannuyten", "bakengroep", "markharbers", "renskeleijten", "piadijkstra", "ninekooiman", "mvantoorenburg", "sachadeboer", "raymondknops", "coosjesmid", "davetromp", "mystoriestotell", "youssef070", "karin_bg", "andypalmen", "yoerialbrecht", "pelleaardema", "nonprofitcoffee", "pum_nl", "regeldit", "regenboogboom", "denoordzee", "waronwant", "josettesheeran", "_amyhorton", "ktchakrabortty", "fairfood", "tonmeijers", "hidschow", "greenbizworld", "s_stone_liberia", "noahgo", "d66_europa", "marliespilon", "advany", "jeroendelange", "mariemant", "linda_polman", "keesvdstaaij", "sanderderouwe", "gerkoopmans", "simonknicholson", "forexlinxie", "vinothorsen", "microsoftedge", "this_is_europe", "saskiadekkers", "neeliekroeseu", "loesjenl", "ckohlmann", "mabelvanoranje", "huubbellemakers", "aartzeeman", "oneworldnl", "groenevoetstap", "ifad", "chantalgk", "yemen_updates", "jgrietman", "lucvanbussel", "wrrdenktank", "usaidgh", "igdleaders", "chinarealtime", "tunkuv", "calestous", "mariahenneman", "wfp_media", "usun", "lvdreep", "ap", "kakoii_en", "qredits", "tineke_strik", "fleurvandissel", "janvberkel", "freeklandmeter", "valerieamos", "dutchmfa", "auswaertigesamt", "esteenhoven", "joeri__boom", "ellendelange", "parlement", "olofvdgaag", "antonyweightman", "bramvank", "asevenstern", "derodehoed", "gbausson", "vprotegenlicht", "asstsecstateaf", "karlrove", "leestewart1", "margjefikse", "nosradio1", "rodrikdani", "sanders225", "daan_cardozo", "daninierenberg", "michielthissen", "business", "stvluchteling", "tnmf", "slaughteram", "shadihamid", "martinchulov", "rajshah", "dicknieuwenhuis", "paulhorsmans", "carlbildt", "nazaninemoshiri", "lrozen", "globalvoices", "columlynch", "isusanstevens", "abakoula", "pointer_kroncrv", "vbtp", "maykesmit", "wyclef", "scclemons", "kmflower", "actionaiduk", "bbclysedoucet", "esj010", "shabablibya", "monqi", "kimghattas", "petra_stienen", "wolfblitzer", "farmingfirst", "ippr", "hansnijenhuis", "jackyaljaz", "yen_li", "mccgov", "melissakchan", "manuelatabb", "carloszarco", "developingjen", "davidroodman", "aiddata", "amisomsomalia", "brandactivist", "elinevbatenburg", "timeline_l", "brookingsglobal", "pwyptweets", "tonyblair_agi", "miekeboots", "paulhilder", "worldresources", "jigsandreels", "alex_jakana", "robf", "lidynic", "inreallive", "jangetkate", "wleenhouts", "oxfamindia", "l_haddad", "ambrice44", "helenclarknz", "eurythmicsultim", "paulienboone", "norishikata", "afritwit", "financien", "autoriteitfm", "cgdev", "annielennox", "keesbroere", "connect4c", "sherinet", "faridtabarki", "w_nuclear_news", "nellekooren", "ikkominactie", "dickberlijn", "fcdogovuk", "oxfamitalia", "fritsbloemberg", "solidaridadnetw", "dutchessdoesldn", "oxfam_de", "ian_black", "guardianworld", "folkert777", "usembassysa", "bw", "ubersoc", "lara", "eucopresident", "dan_nolan9", "alanfisher", "robcrilly", "ifpri", "oxfam_fr", "ajenews", "dgateway", "aidtransparency", "pjcrowley", "haralddoornbos", "fcdoresearch", "sarinamaat", "jack_welch", "alecjross", "nytimesbooks", "coloredopinions", "taxjusticenl", "mariskaaantjes", "jsgravendijk", "opendemocracy", "kieslies", "oxfam_es", "rudolfp", "aymanm", "michaelworley", "torycapital", "ruardganzevoort", "mennospiro", "oscar_soria", "nonprofitorgs", "hrwdispatches", "tonvandenbrink", "alexkaat", "arjanelfassed", "mitchellreports", "roliensasse", "elbaradei", "peter_schong", "mercycorps", "ireenoostveen", "rbreich", "thdegraaf", "hannekevdwerf", "jlatijnhouwers", "hansvandeweerd", "margreetdevries", "michielhendrikx", "tofthissen", "pressfreedom", "sannevroom", "manonuphoff", "offkiltershow", "hrw", "savethechildren", "wwf", "dalailama", "mato74", "emileroemer", "statedept", "usaid", "rubenkoops", "rikreporter", "riseofgenius", "contextnewsroom", "fendius", "ariannahuff", "jacoklamer", "pdjkt", "emmiekollau", "_martinsmit", "annedien", "hpropitius", "ruudvantendris", "guardianeco", "fd_nieuws", "jaketapper", "mennorigterink", "ickamsterdam", "kajleers", "intlcomms", "sasjabokkerink", "joepverboeket", "worldvisionusa", "stiglitzian", "traciscampbell", "dmtpruett", "egeldwijzer", "nielsheithuis", "hkranstauber", "rensmensink", "fromdamountain", "azg_nl", "stopaidsnow", "worldvision", "1percentclub", "josdevoogd", "owenbarder", "wilmavdheide", "ilcovanderlinde", "lindyjanssen", "amstermarijn", "postcodeloterij", "sabineblancday", "brutuz", "andrevdstouwe", "thebrokeronline", "huffpost", "welingelicht", "marniemix", "basdevri", "suzannaruis", "bennuworld", "overgangster", "went1955", "cordaid", "margreetvdpijl", "warchildholland", "somo", "leandertijdhof", "edwincrombags", "louis_press", "okoning", "fransbieckmann", "unicef", "rodekruis", "unicefnl", "fatmad66", "maxnanet", "farah_karimi", "minpres", "greenfaucet", "lroozendaal", "diandaveldman", "mlanting", "rvbroekhoven", "reuters", "greenpeace", "annewillucas", "joris_pvda", "herrozoutendijk", "drdigipol", "wecf_nl", "simb0lica", "wecf_int", "jwboissevain", "capaction", "evanroemburg", "twietjes", "marlyboon", "keeskodde", "josvanderlans", "originclear", "bjheijne", "edmundricedev", "annetdejong", "drskee", "jveerden", "ruudii", "rjg76", "bayareadivorce", "sc_seo", "prns", "partosdir", "robmollink", "gijsdewerker", "belindavdgaag", "hansandringa", "nicolemhmetz", "hesterassen", "hanvalk", "katholief", "ivotalsma", "henksjoerd", "vkoblenko", "mysticventures", "oxfameafrica", "mlauriks", "dijkhoff", "robbertvdberg", "mariekehaafkes", "emmaseery", "europanu", "bart_dirks", "robwijnberg", "fonslambie", "nunl", "issuemakers", "luyte", "henkjanormel", "inekedezentje", "jennekevanp", "thespindlenl", "andreplancius", "kgferrier", "stagerepub", "mirjamsterk", "vanbijsterveldt", "adriduivesteijn", "adkoppejan", "dokky", "hermanzaalberg", "birgitdewez", "standupfyrights", "jackontwerp", "afrikaleeuw", "bitsoffreedom", "lotteragut", "pieterhilhorst", "m_nieuwenhuis", "lucasbenschop", "rgeeraedts", "phremarque", "geertwilderspvv", "mennodebruyne", "jacquesmonasch", "tamarasha", "iixglobal", "simonhinton", "sonjasuper", "sanneterlingen", "dutchmen1973", "dinodzankovic", "iucnnl", "theyemennews", "orangegroveband", "steve_ghoerbien", "twopcharts_nl", "bergwijzer", "richardlamb", "marcelkopmels", "dropinthebucket", "john_mathews", "sputteren", "linandjirsa", "tonelias", "jeaninehennis", "hantenbroeke", "arieslob", "sharon_dijksma", "pickensplan", "bertusbouwman", "bashoornnl", "lab51ecommerce", "flickartist", "startuppro", "wakooz_rss", "orrin_woodward", "frankvdlinde", "mmorshuis", "kenkaiseo", "jeroenjansenasn", "beurstweets", "buzzflash", "rikburgersdijk", "hanslaroes", "rutgergw", "abroaderview", "pjotrrrr", "lettydek", "in10", "easypaisa", "petermiddendorp", "bartjanspruyt", "maasmichel", "kindoffensive", "greenpeaceuk", "ed_miliband", "ronfresen", "tveitdal", "carolinelucas", "foreigninvestor", "enoughproject", "gerdaverburg", "jandriessen", "jurjenvdb", "nathalie_gvv", "maartenvdmeer", "annexum_huib", "dominiqueheyde", "andoradmiraal", "pvlangevelde", "ascholtes", "_futurefactor", "atsmajoop", "guidothys", "rutgervz", "vergunst", "rbaruch", "rikgoverde", "vincentsmit", "reafrica1", "degroene", "jpdaems", "joostvullings", "friesemaffia", "jahootsen", "topstardiamond", "viceversanl", "jurr", "teunvandekeuken", "tofikdibi", "natasjavdberg", "groenliesbeth", "nonukescampaign", "paxvoorvrede", "clarifynl", "africabusiness4", "carolw44", "twitting_lawyer", "tomminter", "randyferrell", "sheilasitalsing", "doriendevries", "bushwarriors", "ewoutirrgang", "mariettehamer", "woutervj", "elseboutkan", "larabillierense", "mongabay", "politiq", "nynkelp", "bschermers", "chrislittlecott", "woukevscherrenb", "layladejong", "ellenheeres", "rindadb", "jimmysmet", "abdellahd20020", "sandermager", "lindavoortman", "jmaouche", "gielvds", "henkstrikkers", "elinevn", "petervermaas", "attjekuiken", "dolfjansen", "edanker", "mariannethieme", "pieteromtzigt", "vanhijum", "rendertalgra", "paulusdewilt", "mariannegybels", "samirbashara", "marije_c", "kapitein", "mnillessen", "jordendebouve", "robynomo", "sjoerdkuiper", "truusk", "carolienkern", "estherdecharon", "iucnredlist", "altenergywebpar", "caroline2market", "patricklacroix", "astridkuiper", "fhi360", "hashtagsdef", "nadyadotnl", "marietjeschaake", "rickvanderkleij", "ivothijssen", "jeroenvdkoppel", "modernarttweets", "billgates", "henknijhof", "enroutes", "tinekeceelen", "awakeningaimee", "chinabizwatch", "bborsje", "collchris", "dwars", "bytje", "idoverhagen", "ja_bakker", "liefdevollid", "helenkuyper", "paulkrugman", "fritswester", "ronaldklip", "inastrating", "erikmouthaanrtl", "kroossara", "carogluck", "ria_bierman", "iiea", "harrieli", "lviss", "zeitgeistlondon", "blazing", "makkinga", "joop_nl", "maartenvdheuvel", "spiegel_english", "financialtimes", "ajenglish", "bbcworld", "worldpolicy", "thenation", "chathamhouse", "usglc", "imfnews", "refugees", "world_affairs", "life", "brookingsfp", "thehill", "amanpour", "foreignaffairs", "thefaketory", "luciastapeen", "michaelm_nft", "petradeboevere", "operationfollow", "rooskorste", "arebacollins", "artistshub", "dijkshoorn", "eefvanbe", "drspi", "jochemspoor", "essen2punt0", "sellmewhatiwant", "fncdialogue", "dubaify", "daanste", "makmende_media", "eglantinazingg", "mariekemonden", "rinihartman", "haagsche", "oikocredit", "zia505", "lateaserikard", "stevenrobello", "saverwanda", "markdnicholls", "dianazwerink", "juliawouters", "stefanverwer", "localscale", "hivos", "mrsvanderlinden", "sophieintveld", "claudiadebreij", "guardiannews", "rosiedbennett", "osocio", "maksimzhdan", "roydawn", "fusto", "baskoers", "vandermieden", "butterflyworks", "sgaster", "1procentclub", "ewoudbutter", "debalie", "globalhealth", "undp", "unaids", "forumone", "financialaccess", "cgap", "cfr_org", "nouriel", "fightpoverty", "dfid_uk", "oxfamhongkong", "doenersnet", "naimaazough", "carbonreductive", "thegreenparty", "inekevangent", "donmacleod", "nielsvdberge", "simonotjes", "bodylef", "kleinlooh", "opfistula", "pietlangendijk", "avaaz", "wilmaborgman", "stockguru_nl", "marjofrenk", "pathway25", "jolvansan", "wluit", "larryjaffe", "loeschout", "ottokamsteeg", "eelcobvr", "lotvanhooijdonk", "_danibal", "svte", "vdwvm", "sjakka", "keesvendrik", "bartsnels", "piece2dot0", "uweskrzypczak", "ghettomat", "fexter", "pritt", "kustawbessems", "barrysmit", "fennaulichki", "wilfrieddejong", "bertbakker", "johnwanders", "addieschulte", "diederiksamsom", "sdinjens", "josheymans", "tijsvandenbrink", "roelienakse", "margreetvanbeem", "ahmedmarcouch", "scaleupanna", "mauricedehond", "brechtje", "kathalijne", "frxnsien", "abrasimzz", "solar4life", "ibnkafka", "2525", "breakingnews", "mbreedveld", "haagseperikelen", "hpdetijdnl", "bertvanslooten", "baspaternotte", "jpgeelen", "fatimaelatik", "liavanbekhoven", "evertdev", "youpvanthek", "stevenfung", "janhart", "rogerhamilton", "richardwouters", "kaatmossel", "alessandraco", "weknowmore", "motivatecanada", "anitadehorde", "hhi", "crisisgroup", "a24media", "aharon72", "zpycer", "hbinnema", "treebanker", "friends_earth", "fairtradenl", "unfccc", "climatenews", "carbonfinance", "unep", "dutchmicrofund", "superrlinda", "dolstra", "queenrania", "locuta", "jilevin", "p4hr", "georgetownmsfs", "michielmulder", "kysia", "apjvalk", "adformatie", "jaapjansen", "jonhutson", "stevebrant", "socialeurope", "future500", "opensociety", "unicefcanada", "oxfamaustralia", "oxfamcanada", "oxfamireland", "bartlacroix", "noreenahertz", "worldconnectors", "tedtalks", "pja64x", "nlm_n", "alanna_shaikh", "lpolgreen", "globalgiving", "allafrica", "amnestyusa", "foreignpolicy", "arenda", "nybooks", "rescueorg", "unrefugeeagency", "heifer", "columbiaclimate", "tedchris", "wfp", "bamakoise", "deviatar", "strasser", "un", "ccoyne1", "aidnews", "davidsteven", "davidmwessel", "wsjecon", "unfoundation", "onecampaign", "kiva", "gatesfoundation", "fao", "nickkristof", "bill_easterly", "hungernomore", "worldtradelaw", "oecd", "globalintegrity", "harvard_law", "huffpostpol", "wpreview", "globaljusticeuk", "fairtradephil", "greenworkslinks", "a4id", "nyu_dri", "odi_global", "cnnafrica", "vc4africa", "academy_centa", "theafronews", "greenpeaceafric", "natgeo", "greentravel", "ecogreentravel", "africafreak", "tomlawmedia", "oxfamamerica", "oxfamgb", "camfed", "wwfclimatebiz", "redcross", "ecointeractive", "janefonda", "mrdannyglover", "wsj", "wef", "nprpolitics", "theonion", "time", "oprah", "algore", "eco_nomy", "bbcafrica", "pazasauti", "nature_kenya", "africanwellfund", "itnewsafrica", "africastrategy", "foluke", "sheblossoms", "learcapital", "d66", "bertwagendorp", "theeconomist", "khalidensophie", "rutger_zelf", "ewmagazinenl", "gstephanopoulos", "sesajas", "jeanfransman", "dambisamoyo", "bbcbreaking", "ajboekestijn", "milieudefensie", "cdavandaag", "martijnvdam", "jesseklaver", "cnnbrk", "newsweek", "nytimes", "nrcslimleven", "nrc", "volkskrant", "geenstijl", "washingtonpost", "postpolls", "cnni", "andriesgknevel", "lodewijka", "rtlnieuws", "10downingstreet", "jeroendegraaf", "obamawhitehouse", "whitehouse45", "mkampschreur", "teletekst", "barackobama", "op1npo", "joostlagendijk", "npopolitiek", "greenpeacenl", "alexklusman", "erikvanbruggen", "heleenmees", "politieke_b", "hansanker", "meuspoel", "jackdevries", "monicamaassen", "rietveld", "michelk", "arjencito", "timjv", "rietjer", "groenlinks", "apechtold", "arnoudboer", "selcuk_nl", "thepoliticus", "paultang", "borisham", "meilivos", "marijec", "baseickhout", "judithsargentin", "jaapdebruijn", "maximeverhagen"]}