{"naam": "Werner, L.M.", "partij": "CDA", "heeftTwitter": true, "twitterHandle": "lucillewerner", "follows": ["vandaaginside", "barackobama", "potus45", "omroepbrabant", "iederin", "niels_krol", "astro_matthias", "mmkamphorst", "esa_nl", "humbertortl", "persveilig", "renkemaerica", "vanranstmarc", "scholtetim", "linda_akkermans", "paul_van_meenen", "fonda_sahla", "momohandis", "jochem_vrugt", "ongehoordnedtv", "boykoborissov", "cqualtro", "heleenvanroyen", "marcelhahne", "lisaginneken", "lisawesterveld", "swsjoerdsma", "peterkwint", "hattevdwoude", "habtamudehoop", "jeanetvdlaan", "fleuragemapvv", "yoerialbrecht", "theaterkrant", "rce_erfgoed", "concertgebouw", "na_archief", "npo2extra", "sjoerdfeitsma", "dekleinekomedie", "vrembrandt", "claudiadebreij", "filmfonds", "denniswiersma", "museumverenigin", "raadvoorcultuur", "rijksmuseum", "cornaldm", "gunayuslu", "arieslob", "robjetten", "hermans_sophie", "kajsaollongren", "maartenooijen", "rhdijkgraaf", "ministerlzs", "ministervws", "berthuisjes", "pimvanstrien", "vera_bergkamp", "annemeithenl", "geertwilderspvv", "artsvg", "wbhoekstra", "henkwillemlaan", "meermuziekklas", "riahghorenga", "lientje1967", "boerburgerb", "ayfer_koc", "cielstevensnl", "sabineuitslag", "houtman_laurens", "wouterkeller", "2ekamertweets", "pieterkleinntr", "wilmaborgman", "minpres", "keesboonman", "xandervdwulp", "fransweisglas", "dit_is_m", "marchaverkamp", "cda_pride", "elshofbj", "cdavandaag", "raymondknops", "pieterheerma", "pieteromtzigt", "i_dijk", "monakeijzer", "jacogeurts", "annekuik", "rutgerploum", "jobacda", "op1npo", "hugodejonge", "svenromkes", "npo1", "kroncrv", "adnl", "esthervergeer", "chris_vos_", "jan_slagter", "tonfvandijk", "lammert", "avrotros", "nos", "koninklijkhuis", "lwfnl", "publiekeomroep", "jancaronie", "hadassahdeboer", "ghislaine_e", "hjengelhardt", "gehandicaptkind", "jedidjahkuijten", "fritshuffnagel", "mechteldvdbeld", "wimvandecamp", "jpnl", "fritswester", "margreetdevries", "servaassnoeijer", "jpbalkenende", "jackdevries", "gerardekdom", "petervdvorst"]}